[
  {
    "timestamp": 1580515200.0,
    "longitude": "-0.111497",
    "latitude": "51.518226",
    "crimeType": "Anti-social behaviour"
  },
  {
    "timestamp": 1580515200.0,
    "longitude": "-0.111962",
    "latitude": "51.518494",
    "crimeType": "Anti-social behaviour"
  },
  {
    "timestamp": 1580515200.0,
    "longitude": "-0.111497",
    "latitude": "51.518226",
    "crimeType": "Other theft"
  },
  {
    "timestamp": 1580515200.0,
    "longitude": "-0.111497",
    "latitude": "51.518226",
    "crimeType": "Theft from the person"
  },
  {
    "timestamp": 1580515200.0,
    "longitude": "-0.111497",
    "latitude": "51.518226",
    "crimeType": "Violence and sexual offences"
  },
  {
    "timestamp": 1580515200.0,
    "longitude": "-0.111962",
    "latitude": "51.518494",
    "crimeType": "Other crime"
  },
  {
    "timestamp": 1580515200.0,
    "longitude": "-0.123317",
    "latitude": "51.515412",
    "crimeType": "Drugs"
  },
  {
    "timestamp": 1580515200.0,
    "longitude": "-0.097601",
    "latitude": "51.520699",
    "crimeType": "Anti-social behaviour"
  },
  {
    "timestamp": 1580515200.0,
    "longitude": "-0.098023",
    "latitude": "51.519905",
    "crimeType": "Anti-social behaviour"
  },
  {
    "timestamp": 1580515200.0,
    "longitude": "-0.097334",
    "latitude": "51.521567",
    "crimeType": "Anti-social behaviour"
  },
  {
    "timestamp": 1580515200.0,
    "longitude": "-0.097562",
    "latitude": "51.518864",
    "crimeType": "Anti-social behaviour"
  },
  {
    "timestamp": 1580515200.0,
    "longitude": "-0.098062",
    "latitude": "51.517577",
    "crimeType": "Anti-social behaviour"
  },
  {
    "timestamp": 1580515200.0,
    "longitude": "-0.098062",
    "latitude": "51.517577",
    "crimeType": "Bicycle theft"
  },
  {
    "timestamp": 1580515200.0,
    "longitude": "-0.097562",
    "latitude": "51.518864",
    "crimeType": "Drugs"
  },
  {
    "timestamp": 1580515200.0,
    "longitude": "-0.097562",
    "latitude": "51.518864",
    "crimeType": "Drugs"
  },
  {
    "timestamp": 1580515200.0,
    "longitude": "-0.097736",
    "latitude": "51.520206",
    "crimeType": "Other theft"
  },
  {
    "timestamp": 1580515200.0,
    "longitude": "-0.097736",
    "latitude": "51.520206",
    "crimeType": "Other theft"
  },
  {
    "timestamp": 1580515200.0,
    "longitude": "-0.095960",
    "latitude": "51.517534",
    "crimeType": "Other theft"
  },
  {
    "timestamp": 1580515200.0,
    "longitude": "-0.097736",
    "latitude": "51.520206",
    "crimeType": "Other theft"
  },
  {
    "timestamp": 1580515200.0,
    "longitude": "-0.097736",
    "latitude": "51.520206",
    "crimeType": "Other theft"
  },
  {
    "timestamp": 1580515200.0,
    "longitude": "-0.098642",
    "latitude": "51.517146",
    "crimeType": "Other theft"
  },
  {
    "timestamp": 1580515200.0,
    "longitude": "-0.098062",
    "latitude": "51.517577",
    "crimeType": "Other theft"
  },
  {
    "timestamp": 1580515200.0,
    "longitude": "-0.097277",
    "latitude": "51.515307",
    "crimeType": "Shoplifting"
  },
  {
    "timestamp": 1580515200.0,
    "longitude": "-0.097601",
    "latitude": "51.520699",
    "crimeType": "Theft from the person"
  },
  {
    "timestamp": 1580515200.0,
    "longitude": "-0.095960",
    "latitude": "51.517534",
    "crimeType": "Theft from the person"
  },
  {
    "timestamp": 1580515200.0,
    "longitude": "-0.097053",
    "latitude": "51.518262",
    "crimeType": "Vehicle crime"
  },
  {
    "timestamp": 1580515200.0,
    "longitude": "-0.097053",
    "latitude": "51.518262",
    "crimeType": "Vehicle crime"
  },
  {
    "timestamp": 1580515200.0,
    "longitude": "-0.097053",
    "latitude": "51.518262",
    "crimeType": "Vehicle crime"
  },
  {
    "timestamp": 1580515200.0,
    "longitude": "-0.097053",
    "latitude": "51.518262",
    "crimeType": "Vehicle crime"
  },
  {
    "timestamp": 1580515200.0,
    "longitude": "-0.097053",
    "latitude": "51.518262",
    "crimeType": "Vehicle crime"
  },
  {
    "timestamp": 1580515200.0,
    "longitude": "-0.097053",
    "latitude": "51.518262",
    "crimeType": "Vehicle crime"
  },
  {
    "timestamp": 1580515200.0,
    "longitude": "-0.097736",
    "latitude": "51.520206",
    "crimeType": "Violence and sexual offences"
  },
  {
    "timestamp": 1580515200.0,
    "longitude": "-0.097334",
    "latitude": "51.521567",
    "crimeType": "Violence and sexual offences"
  },
  {
    "timestamp": 1580515200.0,
    "longitude": "-0.098642",
    "latitude": "51.517146",
    "crimeType": "Violence and sexual offences"
  },
  {
    "timestamp": 1580515200.0,
    "longitude": "-0.097334",
    "latitude": "51.521567",
    "crimeType": "Violence and sexual offences"
  },
  {
    "timestamp": 1580515200.0,
    "longitude": "-0.097601",
    "latitude": "51.520699",
    "crimeType": "Violence and sexual offences"
  },
  {
    "timestamp": 1580515200.0,
    "longitude": "-0.093948",
    "latitude": "51.518077",
    "crimeType": "Anti-social behaviour"
  },
  {
    "timestamp": 1580515200.0,
    "longitude": "-0.094546",
    "latitude": "51.520658",
    "crimeType": "Anti-social behaviour"
  },
  {
    "timestamp": 1580515200.0,
    "longitude": "-0.092297",
    "latitude": "51.518949",
    "crimeType": "Criminal damage and arson"
  },
  {
    "timestamp": 1580515200.0,
    "longitude": "-0.094115",
    "latitude": "51.516497",
    "crimeType": "Criminal damage and arson"
  },
  {
    "timestamp": 1580515200.0,
    "longitude": "-0.094094",
    "latitude": "51.515606",
    "crimeType": "Drugs"
  },
  {
    "timestamp": 1580515200.0,
    "longitude": "-0.094582",
    "latitude": "51.517376",
    "crimeType": "Other theft"
  },
  {
    "timestamp": 1580515200.0,
    "longitude": "-0.094094",
    "latitude": "51.515606",
    "crimeType": "Other theft"
  },
  {
    "timestamp": 1580515200.0,
    "longitude": "-0.089596",
    "latitude": "51.518743",
    "crimeType": "Other theft"
  },
  {
    "timestamp": 1580515200.0,
    "longitude": "-0.088621",
    "latitude": "51.518619",
    "crimeType": "Other theft"
  },
  {
    "timestamp": 1580515200.0,
    "longitude": "-0.093933",
    "latitude": "51.519812",
    "crimeType": "Other theft"
  },
  {
    "timestamp": 1580515200.0,
    "longitude": "-0.092297",
    "latitude": "51.518949",
    "crimeType": "Other theft"
  },
  {
    "timestamp": 1580515200.0,
    "longitude": "-0.094094",
    "latitude": "51.515606",
    "crimeType": "Possession of weapons"
  },
  {
    "timestamp": 1580515200.0,
    "longitude": "-0.092628",
    "latitude": "51.517920",
    "crimeType": "Robbery"
  },
  {
    "timestamp": 1580515200.0,
    "longitude": "-0.088621",
    "latitude": "51.518619",
    "crimeType": "Shoplifting"
  },
  {
    "timestamp": 1580515200.0,
    "longitude": "-0.088621",
    "latitude": "51.518619",
    "crimeType": "Shoplifting"
  },
  {
    "timestamp": 1580515200.0,
    "longitude": "-0.094094",
    "latitude": "51.515606",
    "crimeType": "Theft from the person"
  },
  {
    "timestamp": 1580515200.0,
    "longitude": "-0.088621",
    "latitude": "51.518619",
    "crimeType": "Theft from the person"
  },
  {
    "timestamp": 1580515200.0,
    "longitude": "-0.092628",
    "latitude": "51.517920",
    "crimeType": "Violence and sexual offences"
  },
  {
    "timestamp": 1580515200.0,
    "longitude": "-0.091440",
    "latitude": "51.519807",
    "crimeType": "Violence and sexual offences"
  },
  {
    "timestamp": 1580515200.0,
    "longitude": "-0.094094",
    "latitude": "51.515606",
    "crimeType": "Violence and sexual offences"
  },
  {
    "timestamp": 1580515200.0,
    "longitude": "-0.094033",
    "latitude": "51.520875",
    "crimeType": "Anti-social behaviour"
  },
  {
    "timestamp": 1580515200.0,
    "longitude": "-0.095381",
    "latitude": "51.521391",
    "crimeType": "Other theft"
  },
  {
    "timestamp": 1580515200.0,
    "longitude": "-0.095381",
    "latitude": "51.521391",
    "crimeType": "Theft from the person"
  },
  {
    "timestamp": 1580515200.0,
    "longitude": "-0.094468",
    "latitude": "51.521853",
    "crimeType": "Theft from the person"
  },
  {
    "timestamp": 1580515200.0,
    "longitude": "-0.094468",
    "latitude": "51.521853",
    "crimeType": "Vehicle crime"
  },
  {
    "timestamp": 1580515200.0,
    "longitude": "-0.077596",
    "latitude": "51.515849",
    "crimeType": "Anti-social behaviour"
  },
  {
    "timestamp": 1580515200.0,
    "longitude": "-0.075146",
    "latitude": "51.513435",
    "crimeType": "Anti-social behaviour"
  },
  {
    "timestamp": 1580515200.0,
    "longitude": "-0.075508",
    "latitude": "51.514763",
    "crimeType": "Anti-social behaviour"
  },
  {
    "timestamp": 1580515200.0,
    "longitude": "-0.074115",
    "latitude": "51.511224",
    "crimeType": "Anti-social behaviour"
  },
  {
    "timestamp": 1580515200.0,
    "longitude": "-0.077451",
    "latitude": "51.515523",
    "crimeType": "Anti-social behaviour"
  },
  {
    "timestamp": 1580515200.0,
    "longitude": "-0.077224",
    "latitude": "51.516122",
    "crimeType": "Anti-social behaviour"
  },
  {
    "timestamp": 1580515200.0,
    "longitude": "-0.075146",
    "latitude": "51.513435",
    "crimeType": "Anti-social behaviour"
  },
  {
    "timestamp": 1580515200.0,
    "longitude": "-0.076113",
    "latitude": "51.511014",
    "crimeType": "Anti-social behaviour"
  },
  {
    "timestamp": 1580515200.0,
    "longitude": "-0.075196",
    "latitude": "51.512609",
    "crimeType": "Anti-social behaviour"
  },
  {
    "timestamp": 1580515200.0,
    "longitude": "-0.074330",
    "latitude": "51.513647",
    "crimeType": "Anti-social behaviour"
  },
  {
    "timestamp": 1580515200.0,
    "longitude": "-0.078250",
    "latitude": "51.515033",
    "crimeType": "Bicycle theft"
  },
  {
    "timestamp": 1580515200.0,
    "longitude": "-0.073254",
    "latitude": "51.512856",
    "crimeType": "Criminal damage and arson"
  },
  {
    "timestamp": 1580515200.0,
    "longitude": "-0.076435",
    "latitude": "51.513627",
    "crimeType": "Criminal damage and arson"
  },
  {
    "timestamp": 1580515200.0,
    "longitude": "-0.077080",
    "latitude": "51.514069",
    "crimeType": "Criminal damage and arson"
  },
  {
    "timestamp": 1580515200.0,
    "longitude": "-0.074958",
    "latitude": "51.514151",
    "crimeType": "Drugs"
  },
  {
    "timestamp": 1580515200.0,
    "longitude": "-0.074958",
    "latitude": "51.514151",
    "crimeType": "Drugs"
  },
  {
    "timestamp": 1580515200.0,
    "longitude": "-0.076459",
    "latitude": "51.513061",
    "crimeType": "Other theft"
  },
  {
    "timestamp": 1580515200.0,
    "longitude": "-0.073065",
    "latitude": "51.511180",
    "crimeType": "Other theft"
  },
  {
    "timestamp": 1580515200.0,
    "longitude": "-0.077513",
    "latitude": "51.515075",
    "crimeType": "Other theft"
  },
  {
    "timestamp": 1580515200.0,
    "longitude": "-0.076435",
    "latitude": "51.513627",
    "crimeType": "Public order"
  },
  {
    "timestamp": 1580515200.0,
    "longitude": "-0.077392",
    "latitude": "51.516233",
    "crimeType": "Public order"
  },
  {
    "timestamp": 1580515200.0,
    "longitude": "-0.077224",
    "latitude": "51.516122",
    "crimeType": "Robbery"
  },
  {
    "timestamp": 1580515200.0,
    "longitude": "-0.079607",
    "latitude": "51.515657",
    "crimeType": "Shoplifting"
  },
  {
    "timestamp": 1580515200.0,
    "longitude": "-0.077513",
    "latitude": "51.515075",
    "crimeType": "Theft from the person"
  },
  {
    "timestamp": 1580515200.0,
    "longitude": "-0.074793",
    "latitude": "51.511208",
    "crimeType": "Theft from the person"
  },
  {
    "timestamp": 1580515200.0,
    "longitude": "-0.074330",
    "latitude": "51.513647",
    "crimeType": "Vehicle crime"
  },
  {
    "timestamp": 1580515200.0,
    "longitude": "-0.078250",
    "latitude": "51.515033",
    "crimeType": "Violence and sexual offences"
  },
  {
    "timestamp": 1580515200.0,
    "longitude": "-0.075196",
    "latitude": "51.512609",
    "crimeType": "Violence and sexual offences"
  },
  {
    "timestamp": 1580515200.0,
    "longitude": "-0.075844",
    "latitude": "51.511594",
    "crimeType": "Violence and sexual offences"
  },
  {
    "timestamp": 1580515200.0,
    "longitude": "-0.076459",
    "latitude": "51.513061",
    "crimeType": "Violence and sexual offences"
  },
  {
    "timestamp": 1580515200.0,
    "longitude": "-0.076435",
    "latitude": "51.513627",
    "crimeType": "Violence and sexual offences"
  },
  {
    "timestamp": 1580515200.0,
    "longitude": "-0.090804",
    "latitude": "51.511560",
    "crimeType": "Anti-social behaviour"
  },
  {
    "timestamp": 1580515200.0,
    "longitude": "-0.080665",
    "latitude": "51.509344",
    "crimeType": "Anti-social behaviour"
  },
  {
    "timestamp": 1580515200.0,
    "longitude": "-0.085257",
    "latitude": "51.511200",
    "crimeType": "Anti-social behaviour"
  },
  {
    "timestamp": 1580515200.0,
    "longitude": "-0.078307",
    "latitude": "51.513676",
    "crimeType": "Anti-social behaviour"
  },
  {
    "timestamp": 1580515200.0,
    "longitude": "-0.077578",
    "latitude": "51.510795",
    "crimeType": "Anti-social behaviour"
  },
  {
    "timestamp": 1580515200.0,
    "longitude": "-0.078856",
    "latitude": "51.518433",
    "crimeType": "Anti-social behaviour"
  },
  {
    "timestamp": 1580515200.0,
    "longitude": "-0.078856",
    "latitude": "51.518433",
    "crimeType": "Anti-social behaviour"
  },
  {
    "timestamp": 1580515200.0,
    "longitude": "-0.101452",
    "latitude": "51.512650",
    "crimeType": "Anti-social behaviour"
  },
  {
    "timestamp": 1580515200.0,
    "longitude": "-0.088473",
    "latitude": "51.518374",
    "crimeType": "Anti-social behaviour"
  },
  {
    "timestamp": 1580515200.0,
    "longitude": "-0.081620",
    "latitude": "51.516814",
    "crimeType": "Anti-social behaviour"
  },
  {
    "timestamp": 1580515200.0,
    "longitude": "-0.082965",
    "latitude": "51.516351",
    "crimeType": "Anti-social behaviour"
  },
  {
    "timestamp": 1580515200.0,
    "longitude": "-0.094628",
    "latitude": "51.514203",
    "crimeType": "Anti-social behaviour"
  },
  {
    "timestamp": 1580515200.0,
    "longitude": "-0.084284",
    "latitude": "51.510671",
    "crimeType": "Anti-social behaviour"
  },
  {
    "timestamp": 1580515200.0,
    "longitude": "-0.081620",
    "latitude": "51.516814",
    "crimeType": "Anti-social behaviour"
  },
  {
    "timestamp": 1580515200.0,
    "longitude": "-0.092625",
    "latitude": "51.513865",
    "crimeType": "Anti-social behaviour"
  },
  {
    "timestamp": 1580515200.0,
    "longitude": "-0.095346",
    "latitude": "51.514970",
    "crimeType": "Anti-social behaviour"
  },
  {
    "timestamp": 1580515200.0,
    "longitude": "-0.084983",
    "latitude": "51.510494",
    "crimeType": "Anti-social behaviour"
  },
  {
    "timestamp": 1580515200.0,
    "longitude": "-0.097699",
    "latitude": "51.511420",
    "crimeType": "Anti-social behaviour"
  },
  {
    "timestamp": 1580515200.0,
    "longitude": "-0.081580",
    "latitude": "51.520510",
    "crimeType": "Anti-social behaviour"
  },
  {
    "timestamp": 1580515200.0,
    "longitude": "-0.082458",
    "latitude": "51.517431",
    "crimeType": "Anti-social behaviour"
  },
  {
    "timestamp": 1580515200.0,
    "longitude": "-0.080376",
    "latitude": "51.517244",
    "crimeType": "Anti-social behaviour"
  },
  {
    "timestamp": 1580515200.0,
    "longitude": "-0.097699",
    "latitude": "51.511420",
    "crimeType": "Anti-social behaviour"
  },
  {
    "timestamp": 1580515200.0,
    "longitude": "-0.080665",
    "latitude": "51.509344",
    "crimeType": "Anti-social behaviour"
  },
  {
    "timestamp": 1580515200.0,
    "longitude": "-0.079786",
    "latitude": "51.517576",
    "crimeType": "Anti-social behaviour"
  },
  {
    "timestamp": 1580515200.0,
    "longitude": "-0.079613",
    "latitude": "51.517231",
    "crimeType": "Anti-social behaviour"
  },
  {
    "timestamp": 1580515200.0,
    "longitude": "-0.086278",
    "latitude": "51.509876",
    "crimeType": "Anti-social behaviour"
  },
  {
    "timestamp": 1580515200.0,
    "longitude": "-0.096846",
    "latitude": "51.511478",
    "crimeType": "Anti-social behaviour"
  },
  {
    "timestamp": 1580515200.0,
    "longitude": "-0.079786",
    "latitude": "51.517576",
    "crimeType": "Anti-social behaviour"
  },
  {
    "timestamp": 1580515200.0,
    "longitude": "-0.081580",
    "latitude": "51.520510",
    "crimeType": "Anti-social behaviour"
  },
  {
    "timestamp": 1580515200.0,
    "longitude": "-0.079786",
    "latitude": "51.517576",
    "crimeType": "Anti-social behaviour"
  },
  {
    "timestamp": 1580515200.0,
    "longitude": "-0.083386",
    "latitude": "51.509757",
    "crimeType": "Anti-social behaviour"
  },
  {
    "timestamp": 1580515200.0,
    "longitude": "-0.092865",
    "latitude": "51.510182",
    "crimeType": "Anti-social behaviour"
  },
  {
    "timestamp": 1580515200.0,
    "longitude": "-0.094482",
    "latitude": "51.512888",
    "crimeType": "Anti-social behaviour"
  },
  {
    "timestamp": 1580515200.0,
    "longitude": "-0.081516",
    "latitude": "51.510014",
    "crimeType": "Anti-social behaviour"
  },
  {
    "timestamp": 1580515200.0,
    "longitude": "-0.091720",
    "latitude": "51.513454",
    "crimeType": "Anti-social behaviour"
  },
  {
    "timestamp": 1580515200.0,
    "longitude": "-0.084983",
    "latitude": "51.510494",
    "crimeType": "Anti-social behaviour"
  },
  {
    "timestamp": 1580515200.0,
    "longitude": "-0.088203",
    "latitude": "51.518262",
    "crimeType": "Anti-social behaviour"
  },
  {
    "timestamp": 1580515200.0,
    "longitude": "-0.101055",
    "latitude": "51.513552",
    "crimeType": "Anti-social behaviour"
  },
  {
    "timestamp": 1580515200.0,
    "longitude": "-0.097699",
    "latitude": "51.511420",
    "crimeType": "Anti-social behaviour"
  },
  {
    "timestamp": 1580515200.0,
    "longitude": "-0.104001",
    "latitude": "51.513051",
    "crimeType": "Anti-social behaviour"
  },
  {
    "timestamp": 1580515200.0,
    "longitude": "-0.084983",
    "latitude": "51.510494",
    "crimeType": "Anti-social behaviour"
  },
  {
    "timestamp": 1580515200.0,
    "longitude": "-0.081580",
    "latitude": "51.520510",
    "crimeType": "Anti-social behaviour"
  },
  {
    "timestamp": 1580515200.0,
    "longitude": "-0.081620",
    "latitude": "51.516814",
    "crimeType": "Anti-social behaviour"
  },
  {
    "timestamp": 1580515200.0,
    "longitude": "-0.101055",
    "latitude": "51.513552",
    "crimeType": "Anti-social behaviour"
  },
  {
    "timestamp": 1580515200.0,
    "longitude": "-0.092296",
    "latitude": "51.511386",
    "crimeType": "Anti-social behaviour"
  },
  {
    "timestamp": 1580515200.0,
    "longitude": "-0.080376",
    "latitude": "51.517244",
    "crimeType": "Anti-social behaviour"
  },
  {
    "timestamp": 1580515200.0,
    "longitude": "-0.085257",
    "latitude": "51.511200",
    "crimeType": "Anti-social behaviour"
  },
  {
    "timestamp": 1580515200.0,
    "longitude": "-0.088042",
    "latitude": "51.511794",
    "crimeType": "Anti-social behaviour"
  },
  {
    "timestamp": 1580515200.0,
    "longitude": "-0.104494",
    "latitude": "51.509848",
    "crimeType": "Anti-social behaviour"
  },
  {
    "timestamp": 1580515200.0,
    "longitude": "-0.087760",
    "latitude": "51.517149",
    "crimeType": "Bicycle theft"
  },
  {
    "timestamp": 1580515200.0,
    "longitude": "-0.086051",
    "latitude": "51.513569",
    "crimeType": "Bicycle theft"
  },
  {
    "timestamp": 1580515200.0,
    "longitude": "-0.081516",
    "latitude": "51.510014",
    "crimeType": "Bicycle theft"
  },
  {
    "timestamp": 1580515200.0,
    "longitude": "-0.081540",
    "latitude": "51.510806",
    "crimeType": "Bicycle theft"
  },
  {
    "timestamp": 1580515200.0,
    "longitude": "-0.082458",
    "latitude": "51.517431",
    "crimeType": "Bicycle theft"
  },
  {
    "timestamp": 1580515200.0,
    "longitude": "-0.090847",
    "latitude": "51.511237",
    "crimeType": "Bicycle theft"
  },
  {
    "timestamp": 1580515200.0,
    "longitude": "-0.090710",
    "latitude": "51.513132",
    "crimeType": "Bicycle theft"
  },
  {
    "timestamp": 1580515200.0,
    "longitude": "-0.080034",
    "latitude": "51.513389",
    "crimeType": "Bicycle theft"
  },
  {
    "timestamp": 1580515200.0,
    "longitude": "-0.093257",
    "latitude": "51.513920",
    "crimeType": "Bicycle theft"
  },
  {
    "timestamp": 1580515200.0,
    "longitude": "-0.088042",
    "latitude": "51.511794",
    "crimeType": "Bicycle theft"
  },
  {
    "timestamp": 1580515200.0,
    "longitude": "-0.094197",
    "latitude": "51.510734",
    "crimeType": "Bicycle theft"
  },
  {
    "timestamp": 1580515200.0,
    "longitude": "-0.087760",
    "latitude": "51.517149",
    "crimeType": "Bicycle theft"
  },
  {
    "timestamp": 1580515200.0,
    "longitude": "-0.081580",
    "latitude": "51.520510",
    "crimeType": "Bicycle theft"
  },
  {
    "timestamp": 1580515200.0,
    "longitude": "-0.080322",
    "latitude": "51.510651",
    "crimeType": "Bicycle theft"
  },
  {
    "timestamp": 1580515200.0,
    "longitude": "-0.084768",
    "latitude": "51.512882",
    "crimeType": "Burglary"
  },
  {
    "timestamp": 1580515200.0,
    "longitude": "-0.078856",
    "latitude": "51.518433",
    "crimeType": "Burglary"
  },
  {
    "timestamp": 1580515200.0,
    "longitude": "-0.078856",
    "latitude": "51.518433",
    "crimeType": "Burglary"
  },
  {
    "timestamp": 1580515200.0,
    "longitude": "-0.078994",
    "latitude": "51.514137",
    "crimeType": "Burglary"
  },
  {
    "timestamp": 1580515200.0,
    "longitude": "-0.104244",
    "latitude": "51.512749",
    "crimeType": "Burglary"
  },
  {
    "timestamp": 1580515200.0,
    "longitude": "-0.077649",
    "latitude": "51.512181",
    "crimeType": "Burglary"
  },
  {
    "timestamp": 1580515200.0,
    "longitude": "-0.084768",
    "latitude": "51.512882",
    "crimeType": "Burglary"
  },
  {
    "timestamp": 1580515200.0,
    "longitude": "-0.083618",
    "latitude": "51.517288",
    "crimeType": "Burglary"
  },
  {
    "timestamp": 1580515200.0,
    "longitude": "-0.079674",
    "latitude": "51.514409",
    "crimeType": "Burglary"
  },
  {
    "timestamp": 1580515200.0,
    "longitude": "-0.081516",
    "latitude": "51.510014",
    "crimeType": "Burglary"
  },
  {
    "timestamp": 1580515200.0,
    "longitude": "-0.080782",
    "latitude": "51.514804",
    "crimeType": "Criminal damage and arson"
  },
  {
    "timestamp": 1580515200.0,
    "longitude": "-0.079786",
    "latitude": "51.517576",
    "crimeType": "Criminal damage and arson"
  },
  {
    "timestamp": 1580515200.0,
    "longitude": "-0.094720",
    "latitude": "51.514420",
    "crimeType": "Criminal damage and arson"
  },
  {
    "timestamp": 1580515200.0,
    "longitude": "-0.089451",
    "latitude": "51.517032",
    "crimeType": "Criminal damage and arson"
  },
  {
    "timestamp": 1580515200.0,
    "longitude": "-0.084967",
    "latitude": "51.512598",
    "crimeType": "Criminal damage and arson"
  },
  {
    "timestamp": 1580515200.0,
    "longitude": "-0.084251",
    "latitude": "51.520059",
    "crimeType": "Criminal damage and arson"
  },
  {
    "timestamp": 1580515200.0,
    "longitude": "-0.079162",
    "latitude": "51.514940",
    "crimeType": "Criminal damage and arson"
  },
  {
    "timestamp": 1580515200.0,
    "longitude": "-0.093257",
    "latitude": "51.513920",
    "crimeType": "Criminal damage and arson"
  },
  {
    "timestamp": 1580515200.0,
    "longitude": "-0.100748",
    "latitude": "51.515031",
    "crimeType": "Criminal damage and arson"
  },
  {
    "timestamp": 1580515200.0,
    "longitude": "-0.084980",
    "latitude": "51.516078",
    "crimeType": "Criminal damage and arson"
  },
  {
    "timestamp": 1580515200.0,
    "longitude": "-0.087780",
    "latitude": "51.508066",
    "crimeType": "Criminal damage and arson"
  },
  {
    "timestamp": 1580515200.0,
    "longitude": "-0.079786",
    "latitude": "51.517576",
    "crimeType": "Criminal damage and arson"
  },
  {
    "timestamp": 1580515200.0,
    "longitude": "-0.080234",
    "latitude": "51.516855",
    "crimeType": "Criminal damage and arson"
  },
  {
    "timestamp": 1580515200.0,
    "longitude": "-0.087549",
    "latitude": "51.514276",
    "crimeType": "Criminal damage and arson"
  },
  {
    "timestamp": 1580515200.0,
    "longitude": "-0.087780",
    "latitude": "51.508066",
    "crimeType": "Drugs"
  },
  {
    "timestamp": 1580515200.0,
    "longitude": "-0.092077",
    "latitude": "51.512147",
    "crimeType": "Drugs"
  },
  {
    "timestamp": 1580515200.0,
    "longitude": "-0.101452",
    "latitude": "51.512650",
    "crimeType": "Drugs"
  },
  {
    "timestamp": 1580515200.0,
    "longitude": "-0.087780",
    "latitude": "51.508066",
    "crimeType": "Drugs"
  },
  {
    "timestamp": 1580515200.0,
    "longitude": "-0.078749",
    "latitude": "51.520985",
    "crimeType": "Drugs"
  },
  {
    "timestamp": 1580515200.0,
    "longitude": "-0.079398",
    "latitude": "51.516508",
    "crimeType": "Drugs"
  },
  {
    "timestamp": 1580515200.0,
    "longitude": "-0.079786",
    "latitude": "51.517576",
    "crimeType": "Drugs"
  },
  {
    "timestamp": 1580515200.0,
    "longitude": "-0.100822",
    "latitude": "51.511165",
    "crimeType": "Drugs"
  },
  {
    "timestamp": 1580515200.0,
    "longitude": "-0.080665",
    "latitude": "51.509344",
    "crimeType": "Drugs"
  },
  {
    "timestamp": 1580515200.0,
    "longitude": "-0.083386",
    "latitude": "51.509757",
    "crimeType": "Drugs"
  },
  {
    "timestamp": 1580515200.0,
    "longitude": "-0.104494",
    "latitude": "51.509848",
    "crimeType": "Drugs"
  },
  {
    "timestamp": 1580515200.0,
    "longitude": "-0.081620",
    "latitude": "51.516814",
    "crimeType": "Drugs"
  },
  {
    "timestamp": 1580515200.0,
    "longitude": "-0.088203",
    "latitude": "51.518262",
    "crimeType": "Drugs"
  },
  {
    "timestamp": 1580515200.0,
    "longitude": "-0.079398",
    "latitude": "51.516508",
    "crimeType": "Drugs"
  },
  {
    "timestamp": 1580515200.0,
    "longitude": "-0.091506",
    "latitude": "51.513037",
    "crimeType": "Drugs"
  },
  {
    "timestamp": 1580515200.0,
    "longitude": "-0.089451",
    "latitude": "51.517032",
    "crimeType": "Drugs"
  },
  {
    "timestamp": 1580515200.0,
    "longitude": "-0.088203",
    "latitude": "51.518262",
    "crimeType": "Drugs"
  },
  {
    "timestamp": 1580515200.0,
    "longitude": "-0.082458",
    "latitude": "51.517431",
    "crimeType": "Drugs"
  },
  {
    "timestamp": 1580515200.0,
    "longitude": "-0.080573",
    "latitude": "51.516006",
    "crimeType": "Drugs"
  },
  {
    "timestamp": 1580515200.0,
    "longitude": "-0.079398",
    "latitude": "51.516508",
    "crimeType": "Drugs"
  },
  {
    "timestamp": 1580515200.0,
    "longitude": "-0.079786",
    "latitude": "51.517576",
    "crimeType": "Drugs"
  },
  {
    "timestamp": 1580515200.0,
    "longitude": "-0.101452",
    "latitude": "51.512650",
    "crimeType": "Drugs"
  },
  {
    "timestamp": 1580515200.0,
    "longitude": "-0.091506",
    "latitude": "51.513037",
    "crimeType": "Drugs"
  },
  {
    "timestamp": 1580515200.0,
    "longitude": "-0.093493",
    "latitude": "51.513447",
    "crimeType": "Drugs"
  },
  {
    "timestamp": 1580515200.0,
    "longitude": "-0.104494",
    "latitude": "51.509848",
    "crimeType": "Drugs"
  },
  {
    "timestamp": 1580515200.0,
    "longitude": "-0.092077",
    "latitude": "51.512147",
    "crimeType": "Drugs"
  },
  {
    "timestamp": 1580515200.0,
    "longitude": "-0.081938",
    "latitude": "51.513007",
    "crimeType": "Other theft"
  },
  {
    "timestamp": 1580515200.0,
    "longitude": "-0.086175",
    "latitude": "51.510945",
    "crimeType": "Other theft"
  },
  {
    "timestamp": 1580515200.0,
    "longitude": "-0.078665",
    "latitude": "51.509950",
    "crimeType": "Other theft"
  },
  {
    "timestamp": 1580515200.0,
    "longitude": "-0.077655",
    "latitude": "51.514088",
    "crimeType": "Other theft"
  },
  {
    "timestamp": 1580515200.0,
    "longitude": "-0.100202",
    "latitude": "51.513268",
    "crimeType": "Other theft"
  },
  {
    "timestamp": 1580515200.0,
    "longitude": "-0.084284",
    "latitude": "51.510671",
    "crimeType": "Other theft"
  },
  {
    "timestamp": 1580515200.0,
    "longitude": "-0.094482",
    "latitude": "51.512888",
    "crimeType": "Other theft"
  },
  {
    "timestamp": 1580515200.0,
    "longitude": "-0.080322",
    "latitude": "51.510651",
    "crimeType": "Other theft"
  },
  {
    "timestamp": 1580515200.0,
    "longitude": "-0.078665",
    "latitude": "51.509950",
    "crimeType": "Other theft"
  },
  {
    "timestamp": 1580515200.0,
    "longitude": "-0.088843",
    "latitude": "51.509532",
    "crimeType": "Other theft"
  },
  {
    "timestamp": 1580515200.0,
    "longitude": "-0.082628",
    "latitude": "51.518189",
    "crimeType": "Other theft"
  },
  {
    "timestamp": 1580515200.0,
    "longitude": "-0.082628",
    "latitude": "51.518189",
    "crimeType": "Other theft"
  },
  {
    "timestamp": 1580515200.0,
    "longitude": "-0.092077",
    "latitude": "51.512147",
    "crimeType": "Other theft"
  },
  {
    "timestamp": 1580515200.0,
    "longitude": "-0.089475",
    "latitude": "51.513355",
    "crimeType": "Other theft"
  },
  {
    "timestamp": 1580515200.0,
    "longitude": "-0.097645",
    "latitude": "51.515142",
    "crimeType": "Other theft"
  },
  {
    "timestamp": 1580515200.0,
    "longitude": "-0.081620",
    "latitude": "51.516814",
    "crimeType": "Other theft"
  },
  {
    "timestamp": 1580515200.0,
    "longitude": "-0.079786",
    "latitude": "51.517576",
    "crimeType": "Other theft"
  },
  {
    "timestamp": 1580515200.0,
    "longitude": "-0.094464",
    "latitude": "51.512959",
    "crimeType": "Other theft"
  },
  {
    "timestamp": 1580515200.0,
    "longitude": "-0.087670",
    "latitude": "51.516877",
    "crimeType": "Other theft"
  },
  {
    "timestamp": 1580515200.0,
    "longitude": "-0.087670",
    "latitude": "51.516877",
    "crimeType": "Other theft"
  },
  {
    "timestamp": 1580515200.0,
    "longitude": "-0.082458",
    "latitude": "51.517431",
    "crimeType": "Other theft"
  },
  {
    "timestamp": 1580515200.0,
    "longitude": "-0.084967",
    "latitude": "51.512598",
    "crimeType": "Other theft"
  },
  {
    "timestamp": 1580515200.0,
    "longitude": "-0.081620",
    "latitude": "51.516814",
    "crimeType": "Other theft"
  },
  {
    "timestamp": 1580515200.0,
    "longitude": "-0.079195",
    "latitude": "51.513798",
    "crimeType": "Other theft"
  },
  {
    "timestamp": 1580515200.0,
    "longitude": "-0.078488",
    "latitude": "51.517923",
    "crimeType": "Other theft"
  },
  {
    "timestamp": 1580515200.0,
    "longitude": "-0.084983",
    "latitude": "51.510494",
    "crimeType": "Other theft"
  },
  {
    "timestamp": 1580515200.0,
    "longitude": "-0.083972",
    "latitude": "51.510549",
    "crimeType": "Other theft"
  },
  {
    "timestamp": 1580515200.0,
    "longitude": "-0.083296",
    "latitude": "51.517058",
    "crimeType": "Other theft"
  },
  {
    "timestamp": 1580515200.0,
    "longitude": "-0.082965",
    "latitude": "51.516351",
    "crimeType": "Other theft"
  },
  {
    "timestamp": 1580515200.0,
    "longitude": "-0.081549",
    "latitude": "51.511625",
    "crimeType": "Other theft"
  },
  {
    "timestamp": 1580515200.0,
    "longitude": "-0.101055",
    "latitude": "51.513552",
    "crimeType": "Other theft"
  },
  {
    "timestamp": 1580515200.0,
    "longitude": "-0.094482",
    "latitude": "51.512888",
    "crimeType": "Other theft"
  },
  {
    "timestamp": 1580515200.0,
    "longitude": "-0.080234",
    "latitude": "51.516855",
    "crimeType": "Other theft"
  },
  {
    "timestamp": 1580515200.0,
    "longitude": "-0.077578",
    "latitude": "51.510795",
    "crimeType": "Other theft"
  },
  {
    "timestamp": 1580515200.0,
    "longitude": "-0.086278",
    "latitude": "51.509876",
    "crimeType": "Other theft"
  },
  {
    "timestamp": 1580515200.0,
    "longitude": "-0.085669",
    "latitude": "51.515100",
    "crimeType": "Other theft"
  },
  {
    "timestamp": 1580515200.0,
    "longitude": "-0.079613",
    "latitude": "51.517231",
    "crimeType": "Other theft"
  },
  {
    "timestamp": 1580515200.0,
    "longitude": "-0.086764",
    "latitude": "51.510307",
    "crimeType": "Other theft"
  },
  {
    "timestamp": 1580515200.0,
    "longitude": "-0.102647",
    "latitude": "51.513721",
    "crimeType": "Other theft"
  },
  {
    "timestamp": 1580515200.0,
    "longitude": "-0.096511",
    "latitude": "51.511922",
    "crimeType": "Other theft"
  },
  {
    "timestamp": 1580515200.0,
    "longitude": "-0.090506",
    "latitude": "51.513524",
    "crimeType": "Other theft"
  },
  {
    "timestamp": 1580515200.0,
    "longitude": "-0.077300",
    "latitude": "51.512607",
    "crimeType": "Other theft"
  },
  {
    "timestamp": 1580515200.0,
    "longitude": "-0.079786",
    "latitude": "51.517576",
    "crimeType": "Other theft"
  },
  {
    "timestamp": 1580515200.0,
    "longitude": "-0.092719",
    "latitude": "51.512652",
    "crimeType": "Other theft"
  },
  {
    "timestamp": 1580515200.0,
    "longitude": "-0.088203",
    "latitude": "51.518262",
    "crimeType": "Other theft"
  },
  {
    "timestamp": 1580515200.0,
    "longitude": "-0.091108",
    "latitude": "51.511529",
    "crimeType": "Other theft"
  },
  {
    "timestamp": 1580515200.0,
    "longitude": "-0.079786",
    "latitude": "51.517576",
    "crimeType": "Other theft"
  },
  {
    "timestamp": 1580515200.0,
    "longitude": "-0.078924",
    "latitude": "51.508587",
    "crimeType": "Other theft"
  },
  {
    "timestamp": 1580515200.0,
    "longitude": "-0.079786",
    "latitude": "51.517576",
    "crimeType": "Other theft"
  },
  {
    "timestamp": 1580515200.0,
    "longitude": "-0.078924",
    "latitude": "51.508587",
    "crimeType": "Other theft"
  },
  {
    "timestamp": 1580515200.0,
    "longitude": "-0.081516",
    "latitude": "51.510014",
    "crimeType": "Other theft"
  },
  {
    "timestamp": 1580515200.0,
    "longitude": "-0.082458",
    "latitude": "51.517431",
    "crimeType": "Other theft"
  },
  {
    "timestamp": 1580515200.0,
    "longitude": "-0.079398",
    "latitude": "51.516508",
    "crimeType": "Other theft"
  },
  {
    "timestamp": 1580515200.0,
    "longitude": "-0.100748",
    "latitude": "51.515031",
    "crimeType": "Other theft"
  },
  {
    "timestamp": 1580515200.0,
    "longitude": "-0.101055",
    "latitude": "51.513552",
    "crimeType": "Other theft"
  },
  {
    "timestamp": 1580515200.0,
    "longitude": "-0.094464",
    "latitude": "51.512959",
    "crimeType": "Other theft"
  },
  {
    "timestamp": 1580515200.0,
    "longitude": "-0.092719",
    "latitude": "51.512652",
    "crimeType": "Other theft"
  },
  {
    "timestamp": 1580515200.0,
    "longitude": "-0.088843",
    "latitude": "51.509532",
    "crimeType": "Other theft"
  },
  {
    "timestamp": 1580515200.0,
    "longitude": "-0.088473",
    "latitude": "51.518374",
    "crimeType": "Other theft"
  },
  {
    "timestamp": 1580515200.0,
    "longitude": "-0.092321",
    "latitude": "51.513194",
    "crimeType": "Other theft"
  },
  {
    "timestamp": 1580515200.0,
    "longitude": "-0.092077",
    "latitude": "51.512147",
    "crimeType": "Other theft"
  },
  {
    "timestamp": 1580515200.0,
    "longitude": "-0.090847",
    "latitude": "51.511237",
    "crimeType": "Other theft"
  },
  {
    "timestamp": 1580515200.0,
    "longitude": "-0.085310",
    "latitude": "51.518511",
    "crimeType": "Other theft"
  },
  {
    "timestamp": 1580515200.0,
    "longitude": "-0.086175",
    "latitude": "51.510945",
    "crimeType": "Other theft"
  },
  {
    "timestamp": 1580515200.0,
    "longitude": "-0.086175",
    "latitude": "51.510945",
    "crimeType": "Other theft"
  },
  {
    "timestamp": 1580515200.0,
    "longitude": "-0.084618",
    "latitude": "51.512682",
    "crimeType": "Other theft"
  },
  {
    "timestamp": 1580515200.0,
    "longitude": "-0.083417",
    "latitude": "51.513148",
    "crimeType": "Other theft"
  },
  {
    "timestamp": 1580515200.0,
    "longitude": "-0.082913",
    "latitude": "51.513463",
    "crimeType": "Other theft"
  },
  {
    "timestamp": 1580515200.0,
    "longitude": "-0.079786",
    "latitude": "51.517576",
    "crimeType": "Other theft"
  },
  {
    "timestamp": 1580515200.0,
    "longitude": "-0.079786",
    "latitude": "51.517576",
    "crimeType": "Other theft"
  },
  {
    "timestamp": 1580515200.0,
    "longitude": "-0.101452",
    "latitude": "51.512650",
    "crimeType": "Other theft"
  },
  {
    "timestamp": 1580515200.0,
    "longitude": "-0.096643",
    "latitude": "51.512545",
    "crimeType": "Other theft"
  },
  {
    "timestamp": 1580515200.0,
    "longitude": "-0.091151",
    "latitude": "51.514992",
    "crimeType": "Other theft"
  },
  {
    "timestamp": 1580515200.0,
    "longitude": "-0.080234",
    "latitude": "51.516855",
    "crimeType": "Other theft"
  },
  {
    "timestamp": 1580515200.0,
    "longitude": "-0.089698",
    "latitude": "51.511812",
    "crimeType": "Other theft"
  },
  {
    "timestamp": 1580515200.0,
    "longitude": "-0.078488",
    "latitude": "51.517923",
    "crimeType": "Other theft"
  },
  {
    "timestamp": 1580515200.0,
    "longitude": "-0.094720",
    "latitude": "51.514420",
    "crimeType": "Other theft"
  },
  {
    "timestamp": 1580515200.0,
    "longitude": "-0.093398",
    "latitude": "51.512951",
    "crimeType": "Other theft"
  },
  {
    "timestamp": 1580515200.0,
    "longitude": "-0.089698",
    "latitude": "51.511812",
    "crimeType": "Other theft"
  },
  {
    "timestamp": 1580515200.0,
    "longitude": "-0.086728",
    "latitude": "51.510477",
    "crimeType": "Other theft"
  },
  {
    "timestamp": 1580515200.0,
    "longitude": "-0.086728",
    "latitude": "51.510477",
    "crimeType": "Other theft"
  },
  {
    "timestamp": 1580515200.0,
    "longitude": "-0.079786",
    "latitude": "51.517576",
    "crimeType": "Other theft"
  },
  {
    "timestamp": 1580515200.0,
    "longitude": "-0.101959",
    "latitude": "51.513297",
    "crimeType": "Other theft"
  },
  {
    "timestamp": 1580515200.0,
    "longitude": "-0.084967",
    "latitude": "51.512598",
    "crimeType": "Other theft"
  },
  {
    "timestamp": 1580515200.0,
    "longitude": "-0.084618",
    "latitude": "51.512682",
    "crimeType": "Other theft"
  },
  {
    "timestamp": 1580515200.0,
    "longitude": "-0.086278",
    "latitude": "51.509876",
    "crimeType": "Other theft"
  },
  {
    "timestamp": 1580515200.0,
    "longitude": "-0.097645",
    "latitude": "51.515142",
    "crimeType": "Other theft"
  },
  {
    "timestamp": 1580515200.0,
    "longitude": "-0.093493",
    "latitude": "51.513447",
    "crimeType": "Other theft"
  },
  {
    "timestamp": 1580515200.0,
    "longitude": "-0.089465",
    "latitude": "51.510855",
    "crimeType": "Other theft"
  },
  {
    "timestamp": 1580515200.0,
    "longitude": "-0.088225",
    "latitude": "51.514656",
    "crimeType": "Other theft"
  },
  {
    "timestamp": 1580515200.0,
    "longitude": "-0.086175",
    "latitude": "51.510945",
    "crimeType": "Other theft"
  },
  {
    "timestamp": 1580515200.0,
    "longitude": "-0.096561",
    "latitude": "51.514513",
    "crimeType": "Other theft"
  },
  {
    "timestamp": 1580515200.0,
    "longitude": "-0.094464",
    "latitude": "51.512959",
    "crimeType": "Other theft"
  },
  {
    "timestamp": 1580515200.0,
    "longitude": "-0.085355",
    "latitude": "51.510563",
    "crimeType": "Other theft"
  },
  {
    "timestamp": 1580515200.0,
    "longitude": "-0.089698",
    "latitude": "51.511812",
    "crimeType": "Other theft"
  },
  {
    "timestamp": 1580515200.0,
    "longitude": "-0.088203",
    "latitude": "51.518262",
    "crimeType": "Other theft"
  },
  {
    "timestamp": 1580515200.0,
    "longitude": "-0.079613",
    "latitude": "51.517231",
    "crimeType": "Other theft"
  },
  {
    "timestamp": 1580515200.0,
    "longitude": "-0.097645",
    "latitude": "51.515142",
    "crimeType": "Other theft"
  },
  {
    "timestamp": 1580515200.0,
    "longitude": "-0.094464",
    "latitude": "51.512959",
    "crimeType": "Other theft"
  },
  {
    "timestamp": 1580515200.0,
    "longitude": "-0.094464",
    "latitude": "51.512959",
    "crimeType": "Other theft"
  },
  {
    "timestamp": 1580515200.0,
    "longitude": "-0.092865",
    "latitude": "51.510182",
    "crimeType": "Other theft"
  },
  {
    "timestamp": 1580515200.0,
    "longitude": "-0.088233",
    "latitude": "51.515484",
    "crimeType": "Other theft"
  },
  {
    "timestamp": 1580515200.0,
    "longitude": "-0.086764",
    "latitude": "51.510307",
    "crimeType": "Other theft"
  },
  {
    "timestamp": 1580515200.0,
    "longitude": "-0.084618",
    "latitude": "51.512682",
    "crimeType": "Other theft"
  },
  {
    "timestamp": 1580515200.0,
    "longitude": "-0.078307",
    "latitude": "51.513676",
    "crimeType": "Other theft"
  },
  {
    "timestamp": 1580515200.0,
    "longitude": "-0.077637",
    "latitude": "51.511453",
    "crimeType": "Other theft"
  },
  {
    "timestamp": 1580515200.0,
    "longitude": "-0.090506",
    "latitude": "51.513524",
    "crimeType": "Other theft"
  },
  {
    "timestamp": 1580515200.0,
    "longitude": "-0.085149",
    "latitude": "51.517196",
    "crimeType": "Other theft"
  },
  {
    "timestamp": 1580515200.0,
    "longitude": "-0.090506",
    "latitude": "51.513524",
    "crimeType": "Other theft"
  },
  {
    "timestamp": 1580515200.0,
    "longitude": "-0.083086",
    "latitude": "51.511407",
    "crimeType": "Other theft"
  },
  {
    "timestamp": 1580515200.0,
    "longitude": "-0.086175",
    "latitude": "51.510945",
    "crimeType": "Other theft"
  },
  {
    "timestamp": 1580515200.0,
    "longitude": "-0.078856",
    "latitude": "51.518433",
    "crimeType": "Other theft"
  },
  {
    "timestamp": 1580515200.0,
    "longitude": "-0.079398",
    "latitude": "51.516508",
    "crimeType": "Other theft"
  },
  {
    "timestamp": 1580515200.0,
    "longitude": "-0.092077",
    "latitude": "51.512147",
    "crimeType": "Other theft"
  },
  {
    "timestamp": 1580515200.0,
    "longitude": "-0.086278",
    "latitude": "51.509876",
    "crimeType": "Other theft"
  },
  {
    "timestamp": 1580515200.0,
    "longitude": "-0.086278",
    "latitude": "51.509876",
    "crimeType": "Other theft"
  },
  {
    "timestamp": 1580515200.0,
    "longitude": "-0.086175",
    "latitude": "51.510945",
    "crimeType": "Other theft"
  },
  {
    "timestamp": 1580515200.0,
    "longitude": "-0.085149",
    "latitude": "51.517196",
    "crimeType": "Other theft"
  },
  {
    "timestamp": 1580515200.0,
    "longitude": "-0.081580",
    "latitude": "51.520510",
    "crimeType": "Other theft"
  },
  {
    "timestamp": 1580515200.0,
    "longitude": "-0.080234",
    "latitude": "51.516855",
    "crimeType": "Other theft"
  },
  {
    "timestamp": 1580515200.0,
    "longitude": "-0.078665",
    "latitude": "51.509950",
    "crimeType": "Other theft"
  },
  {
    "timestamp": 1580515200.0,
    "longitude": "-0.100202",
    "latitude": "51.513268",
    "crimeType": "Other theft"
  },
  {
    "timestamp": 1580515200.0,
    "longitude": "-0.082965",
    "latitude": "51.516351",
    "crimeType": "Other theft"
  },
  {
    "timestamp": 1580515200.0,
    "longitude": "-0.083755",
    "latitude": "51.514358",
    "crimeType": "Other theft"
  },
  {
    "timestamp": 1580515200.0,
    "longitude": "-0.080234",
    "latitude": "51.516855",
    "crimeType": "Other theft"
  },
  {
    "timestamp": 1580515200.0,
    "longitude": "-0.093398",
    "latitude": "51.512951",
    "crimeType": "Other theft"
  },
  {
    "timestamp": 1580515200.0,
    "longitude": "-0.090506",
    "latitude": "51.513524",
    "crimeType": "Other theft"
  },
  {
    "timestamp": 1580515200.0,
    "longitude": "-0.085833",
    "latitude": "51.513952",
    "crimeType": "Other theft"
  },
  {
    "timestamp": 1580515200.0,
    "longitude": "-0.081620",
    "latitude": "51.516814",
    "crimeType": "Other theft"
  },
  {
    "timestamp": 1580515200.0,
    "longitude": "-0.080782",
    "latitude": "51.514804",
    "crimeType": "Other theft"
  },
  {
    "timestamp": 1580515200.0,
    "longitude": "-0.079195",
    "latitude": "51.513798",
    "crimeType": "Other theft"
  },
  {
    "timestamp": 1580515200.0,
    "longitude": "-0.084967",
    "latitude": "51.512598",
    "crimeType": "Other theft"
  },
  {
    "timestamp": 1580515200.0,
    "longitude": "-0.080782",
    "latitude": "51.514804",
    "crimeType": "Other theft"
  },
  {
    "timestamp": 1580515200.0,
    "longitude": "-0.094628",
    "latitude": "51.514203",
    "crimeType": "Other theft"
  },
  {
    "timestamp": 1580515200.0,
    "longitude": "-0.079786",
    "latitude": "51.517576",
    "crimeType": "Other theft"
  },
  {
    "timestamp": 1580515200.0,
    "longitude": "-0.088203",
    "latitude": "51.518262",
    "crimeType": "Other theft"
  },
  {
    "timestamp": 1580515200.0,
    "longitude": "-0.083618",
    "latitude": "51.517288",
    "crimeType": "Other theft"
  },
  {
    "timestamp": 1580515200.0,
    "longitude": "-0.086728",
    "latitude": "51.510477",
    "crimeType": "Other theft"
  },
  {
    "timestamp": 1580515200.0,
    "longitude": "-0.091823",
    "latitude": "51.514418",
    "crimeType": "Other theft"
  },
  {
    "timestamp": 1580515200.0,
    "longitude": "-0.086728",
    "latitude": "51.510477",
    "crimeType": "Other theft"
  },
  {
    "timestamp": 1580515200.0,
    "longitude": "-0.078856",
    "latitude": "51.518433",
    "crimeType": "Other theft"
  },
  {
    "timestamp": 1580515200.0,
    "longitude": "-0.093493",
    "latitude": "51.513447",
    "crimeType": "Other theft"
  },
  {
    "timestamp": 1580515200.0,
    "longitude": "-0.092321",
    "latitude": "51.513194",
    "crimeType": "Other theft"
  },
  {
    "timestamp": 1580515200.0,
    "longitude": "-0.083086",
    "latitude": "51.511407",
    "crimeType": "Other theft"
  },
  {
    "timestamp": 1580515200.0,
    "longitude": "-0.080146",
    "latitude": "51.514848",
    "crimeType": "Other theft"
  },
  {
    "timestamp": 1580515200.0,
    "longitude": "-0.092865",
    "latitude": "51.510182",
    "crimeType": "Other theft"
  },
  {
    "timestamp": 1580515200.0,
    "longitude": "-0.086550",
    "latitude": "51.512651",
    "crimeType": "Other theft"
  },
  {
    "timestamp": 1580515200.0,
    "longitude": "-0.097645",
    "latitude": "51.515142",
    "crimeType": "Other theft"
  },
  {
    "timestamp": 1580515200.0,
    "longitude": "-0.079786",
    "latitude": "51.517576",
    "crimeType": "Other theft"
  },
  {
    "timestamp": 1580515200.0,
    "longitude": "-0.090506",
    "latitude": "51.513524",
    "crimeType": "Other theft"
  },
  {
    "timestamp": 1580515200.0,
    "longitude": "-0.101055",
    "latitude": "51.513552",
    "crimeType": "Other theft"
  },
  {
    "timestamp": 1580515200.0,
    "longitude": "-0.081580",
    "latitude": "51.520510",
    "crimeType": "Other theft"
  },
  {
    "timestamp": 1580515200.0,
    "longitude": "-0.078856",
    "latitude": "51.518433",
    "crimeType": "Other theft"
  },
  {
    "timestamp": 1580515200.0,
    "longitude": "-0.095015",
    "latitude": "51.513220",
    "crimeType": "Other theft"
  },
  {
    "timestamp": 1580515200.0,
    "longitude": "-0.087666",
    "latitude": "51.511122",
    "crimeType": "Other theft"
  },
  {
    "timestamp": 1580515200.0,
    "longitude": "-0.095015",
    "latitude": "51.513220",
    "crimeType": "Other theft"
  },
  {
    "timestamp": 1580515200.0,
    "longitude": "-0.094464",
    "latitude": "51.512959",
    "crimeType": "Other theft"
  },
  {
    "timestamp": 1580515200.0,
    "longitude": "-0.092321",
    "latitude": "51.513194",
    "crimeType": "Other theft"
  },
  {
    "timestamp": 1580515200.0,
    "longitude": "-0.089465",
    "latitude": "51.510855",
    "crimeType": "Other theft"
  },
  {
    "timestamp": 1580515200.0,
    "longitude": "-0.078308",
    "latitude": "51.518091",
    "crimeType": "Other theft"
  },
  {
    "timestamp": 1580515200.0,
    "longitude": "-0.084768",
    "latitude": "51.512882",
    "crimeType": "Other theft"
  },
  {
    "timestamp": 1580515200.0,
    "longitude": "-0.082628",
    "latitude": "51.518189",
    "crimeType": "Other theft"
  },
  {
    "timestamp": 1580515200.0,
    "longitude": "-0.088203",
    "latitude": "51.518262",
    "crimeType": "Possession of weapons"
  },
  {
    "timestamp": 1580515200.0,
    "longitude": "-0.092625",
    "latitude": "51.513865",
    "crimeType": "Public order"
  },
  {
    "timestamp": 1580515200.0,
    "longitude": "-0.083296",
    "latitude": "51.517058",
    "crimeType": "Public order"
  },
  {
    "timestamp": 1580515200.0,
    "longitude": "-0.079786",
    "latitude": "51.517576",
    "crimeType": "Public order"
  },
  {
    "timestamp": 1580515200.0,
    "longitude": "-0.080376",
    "latitude": "51.517244",
    "crimeType": "Public order"
  },
  {
    "timestamp": 1580515200.0,
    "longitude": "-0.092625",
    "latitude": "51.513865",
    "crimeType": "Public order"
  },
  {
    "timestamp": 1580515200.0,
    "longitude": "-0.081620",
    "latitude": "51.516814",
    "crimeType": "Public order"
  },
  {
    "timestamp": 1580515200.0,
    "longitude": "-0.086701",
    "latitude": "51.510774",
    "crimeType": "Public order"
  },
  {
    "timestamp": 1580515200.0,
    "longitude": "-0.089435",
    "latitude": "51.511223",
    "crimeType": "Public order"
  },
  {
    "timestamp": 1580515200.0,
    "longitude": "-0.078856",
    "latitude": "51.518433",
    "crimeType": "Public order"
  },
  {
    "timestamp": 1580515200.0,
    "longitude": "-0.080034",
    "latitude": "51.513389",
    "crimeType": "Public order"
  },
  {
    "timestamp": 1580515200.0,
    "longitude": "-0.081620",
    "latitude": "51.516814",
    "crimeType": "Public order"
  },
  {
    "timestamp": 1580515200.0,
    "longitude": "-0.101274",
    "latitude": "51.512791",
    "crimeType": "Public order"
  },
  {
    "timestamp": 1580515200.0,
    "longitude": "-0.101055",
    "latitude": "51.513552",
    "crimeType": "Public order"
  },
  {
    "timestamp": 1580515200.0,
    "longitude": "-0.100748",
    "latitude": "51.515031",
    "crimeType": "Public order"
  },
  {
    "timestamp": 1580515200.0,
    "longitude": "-0.090506",
    "latitude": "51.513524",
    "crimeType": "Public order"
  },
  {
    "timestamp": 1580515200.0,
    "longitude": "-0.094628",
    "latitude": "51.514203",
    "crimeType": "Public order"
  },
  {
    "timestamp": 1580515200.0,
    "longitude": "-0.080322",
    "latitude": "51.510651",
    "crimeType": "Public order"
  },
  {
    "timestamp": 1580515200.0,
    "longitude": "-0.085833",
    "latitude": "51.513952",
    "crimeType": "Public order"
  },
  {
    "timestamp": 1580515200.0,
    "longitude": "-0.081620",
    "latitude": "51.516814",
    "crimeType": "Public order"
  },
  {
    "timestamp": 1580515200.0,
    "longitude": "-0.084983",
    "latitude": "51.510494",
    "crimeType": "Public order"
  },
  {
    "timestamp": 1580515200.0,
    "longitude": "-0.093215",
    "latitude": "51.510421",
    "crimeType": "Public order"
  },
  {
    "timestamp": 1580515200.0,
    "longitude": "-0.081620",
    "latitude": "51.516814",
    "crimeType": "Public order"
  },
  {
    "timestamp": 1580515200.0,
    "longitude": "-0.085833",
    "latitude": "51.513952",
    "crimeType": "Public order"
  },
  {
    "timestamp": 1580515200.0,
    "longitude": "-0.082458",
    "latitude": "51.517431",
    "crimeType": "Public order"
  },
  {
    "timestamp": 1580515200.0,
    "longitude": "-0.084284",
    "latitude": "51.510671",
    "crimeType": "Robbery"
  },
  {
    "timestamp": 1580515200.0,
    "longitude": "-0.082458",
    "latitude": "51.517431",
    "crimeType": "Robbery"
  },
  {
    "timestamp": 1580515200.0,
    "longitude": "-0.092077",
    "latitude": "51.512147",
    "crimeType": "Robbery"
  },
  {
    "timestamp": 1580515200.0,
    "longitude": "-0.081549",
    "latitude": "51.511625",
    "crimeType": "Robbery"
  },
  {
    "timestamp": 1580515200.0,
    "longitude": "-0.094628",
    "latitude": "51.514203",
    "crimeType": "Shoplifting"
  },
  {
    "timestamp": 1580515200.0,
    "longitude": "-0.084967",
    "latitude": "51.512598",
    "crimeType": "Shoplifting"
  },
  {
    "timestamp": 1580515200.0,
    "longitude": "-0.084967",
    "latitude": "51.512598",
    "crimeType": "Shoplifting"
  },
  {
    "timestamp": 1580515200.0,
    "longitude": "-0.083755",
    "latitude": "51.514358",
    "crimeType": "Shoplifting"
  },
  {
    "timestamp": 1580515200.0,
    "longitude": "-0.084967",
    "latitude": "51.512598",
    "crimeType": "Shoplifting"
  },
  {
    "timestamp": 1580515200.0,
    "longitude": "-0.081620",
    "latitude": "51.516814",
    "crimeType": "Shoplifting"
  },
  {
    "timestamp": 1580515200.0,
    "longitude": "-0.093465",
    "latitude": "51.514463",
    "crimeType": "Shoplifting"
  },
  {
    "timestamp": 1580515200.0,
    "longitude": "-0.093465",
    "latitude": "51.514463",
    "crimeType": "Shoplifting"
  },
  {
    "timestamp": 1580515200.0,
    "longitude": "-0.084618",
    "latitude": "51.512682",
    "crimeType": "Shoplifting"
  },
  {
    "timestamp": 1580515200.0,
    "longitude": "-0.088393",
    "latitude": "51.511332",
    "crimeType": "Shoplifting"
  },
  {
    "timestamp": 1580515200.0,
    "longitude": "-0.094628",
    "latitude": "51.514203",
    "crimeType": "Shoplifting"
  },
  {
    "timestamp": 1580515200.0,
    "longitude": "-0.083993",
    "latitude": "51.511440",
    "crimeType": "Shoplifting"
  },
  {
    "timestamp": 1580515200.0,
    "longitude": "-0.079786",
    "latitude": "51.517576",
    "crimeType": "Shoplifting"
  },
  {
    "timestamp": 1580515200.0,
    "longitude": "-0.097645",
    "latitude": "51.515142",
    "crimeType": "Shoplifting"
  },
  {
    "timestamp": 1580515200.0,
    "longitude": "-0.091720",
    "latitude": "51.513454",
    "crimeType": "Shoplifting"
  },
  {
    "timestamp": 1580515200.0,
    "longitude": "-0.096075",
    "latitude": "51.514766",
    "crimeType": "Shoplifting"
  },
  {
    "timestamp": 1580515200.0,
    "longitude": "-0.086166",
    "latitude": "51.510828",
    "crimeType": "Shoplifting"
  },
  {
    "timestamp": 1580515200.0,
    "longitude": "-0.079786",
    "latitude": "51.517576",
    "crimeType": "Shoplifting"
  },
  {
    "timestamp": 1580515200.0,
    "longitude": "-0.080782",
    "latitude": "51.514804",
    "crimeType": "Shoplifting"
  },
  {
    "timestamp": 1580515200.0,
    "longitude": "-0.091720",
    "latitude": "51.513454",
    "crimeType": "Shoplifting"
  },
  {
    "timestamp": 1580515200.0,
    "longitude": "-0.084983",
    "latitude": "51.510494",
    "crimeType": "Shoplifting"
  },
  {
    "timestamp": 1580515200.0,
    "longitude": "-0.097645",
    "latitude": "51.515142",
    "crimeType": "Shoplifting"
  },
  {
    "timestamp": 1580515200.0,
    "longitude": "-0.084967",
    "latitude": "51.512598",
    "crimeType": "Shoplifting"
  },
  {
    "timestamp": 1580515200.0,
    "longitude": "-0.084967",
    "latitude": "51.512598",
    "crimeType": "Shoplifting"
  },
  {
    "timestamp": 1580515200.0,
    "longitude": "-0.080376",
    "latitude": "51.517244",
    "crimeType": "Shoplifting"
  },
  {
    "timestamp": 1580515200.0,
    "longitude": "-0.104244",
    "latitude": "51.512749",
    "crimeType": "Shoplifting"
  },
  {
    "timestamp": 1580515200.0,
    "longitude": "-0.083645",
    "latitude": "51.512504",
    "crimeType": "Shoplifting"
  },
  {
    "timestamp": 1580515200.0,
    "longitude": "-0.084967",
    "latitude": "51.512598",
    "crimeType": "Shoplifting"
  },
  {
    "timestamp": 1580515200.0,
    "longitude": "-0.094628",
    "latitude": "51.514203",
    "crimeType": "Shoplifting"
  },
  {
    "timestamp": 1580515200.0,
    "longitude": "-0.080376",
    "latitude": "51.517244",
    "crimeType": "Shoplifting"
  },
  {
    "timestamp": 1580515200.0,
    "longitude": "-0.086551",
    "latitude": "51.511616",
    "crimeType": "Shoplifting"
  },
  {
    "timestamp": 1580515200.0,
    "longitude": "-0.080376",
    "latitude": "51.517244",
    "crimeType": "Shoplifting"
  },
  {
    "timestamp": 1580515200.0,
    "longitude": "-0.084967",
    "latitude": "51.512598",
    "crimeType": "Shoplifting"
  },
  {
    "timestamp": 1580515200.0,
    "longitude": "-0.091720",
    "latitude": "51.513454",
    "crimeType": "Shoplifting"
  },
  {
    "timestamp": 1580515200.0,
    "longitude": "-0.080376",
    "latitude": "51.517244",
    "crimeType": "Shoplifting"
  },
  {
    "timestamp": 1580515200.0,
    "longitude": "-0.084967",
    "latitude": "51.512598",
    "crimeType": "Shoplifting"
  },
  {
    "timestamp": 1580515200.0,
    "longitude": "-0.104244",
    "latitude": "51.512749",
    "crimeType": "Shoplifting"
  },
  {
    "timestamp": 1580515200.0,
    "longitude": "-0.096363",
    "latitude": "51.513377",
    "crimeType": "Shoplifting"
  },
  {
    "timestamp": 1580515200.0,
    "longitude": "-0.097645",
    "latitude": "51.515142",
    "crimeType": "Shoplifting"
  },
  {
    "timestamp": 1580515200.0,
    "longitude": "-0.086166",
    "latitude": "51.510828",
    "crimeType": "Shoplifting"
  },
  {
    "timestamp": 1580515200.0,
    "longitude": "-0.096363",
    "latitude": "51.513377",
    "crimeType": "Shoplifting"
  },
  {
    "timestamp": 1580515200.0,
    "longitude": "-0.079786",
    "latitude": "51.517576",
    "crimeType": "Shoplifting"
  },
  {
    "timestamp": 1580515200.0,
    "longitude": "-0.104244",
    "latitude": "51.512749",
    "crimeType": "Shoplifting"
  },
  {
    "timestamp": 1580515200.0,
    "longitude": "-0.079786",
    "latitude": "51.517576",
    "crimeType": "Shoplifting"
  },
  {
    "timestamp": 1580515200.0,
    "longitude": "-0.079786",
    "latitude": "51.517576",
    "crimeType": "Shoplifting"
  },
  {
    "timestamp": 1580515200.0,
    "longitude": "-0.104001",
    "latitude": "51.513051",
    "crimeType": "Shoplifting"
  },
  {
    "timestamp": 1580515200.0,
    "longitude": "-0.080782",
    "latitude": "51.514804",
    "crimeType": "Shoplifting"
  },
  {
    "timestamp": 1580515200.0,
    "longitude": "-0.084967",
    "latitude": "51.512598",
    "crimeType": "Shoplifting"
  },
  {
    "timestamp": 1580515200.0,
    "longitude": "-0.096075",
    "latitude": "51.514766",
    "crimeType": "Shoplifting"
  },
  {
    "timestamp": 1580515200.0,
    "longitude": "-0.092380",
    "latitude": "51.513510",
    "crimeType": "Shoplifting"
  },
  {
    "timestamp": 1580515200.0,
    "longitude": "-0.095015",
    "latitude": "51.513220",
    "crimeType": "Shoplifting"
  },
  {
    "timestamp": 1580515200.0,
    "longitude": "-0.084967",
    "latitude": "51.512598",
    "crimeType": "Shoplifting"
  },
  {
    "timestamp": 1580515200.0,
    "longitude": "-0.086166",
    "latitude": "51.510828",
    "crimeType": "Shoplifting"
  },
  {
    "timestamp": 1580515200.0,
    "longitude": "-0.092625",
    "latitude": "51.513865",
    "crimeType": "Shoplifting"
  },
  {
    "timestamp": 1580515200.0,
    "longitude": "-0.084199",
    "latitude": "51.513394",
    "crimeType": "Shoplifting"
  },
  {
    "timestamp": 1580515200.0,
    "longitude": "-0.091720",
    "latitude": "51.513454",
    "crimeType": "Shoplifting"
  },
  {
    "timestamp": 1580515200.0,
    "longitude": "-0.089435",
    "latitude": "51.511223",
    "crimeType": "Shoplifting"
  },
  {
    "timestamp": 1580515200.0,
    "longitude": "-0.080376",
    "latitude": "51.517244",
    "crimeType": "Shoplifting"
  },
  {
    "timestamp": 1580515200.0,
    "longitude": "-0.085257",
    "latitude": "51.511200",
    "crimeType": "Shoplifting"
  },
  {
    "timestamp": 1580515200.0,
    "longitude": "-0.084967",
    "latitude": "51.512598",
    "crimeType": "Shoplifting"
  },
  {
    "timestamp": 1580515200.0,
    "longitude": "-0.081620",
    "latitude": "51.516814",
    "crimeType": "Shoplifting"
  },
  {
    "timestamp": 1580515200.0,
    "longitude": "-0.097645",
    "latitude": "51.515142",
    "crimeType": "Shoplifting"
  },
  {
    "timestamp": 1580515200.0,
    "longitude": "-0.089698",
    "latitude": "51.511812",
    "crimeType": "Shoplifting"
  },
  {
    "timestamp": 1580515200.0,
    "longitude": "-0.097645",
    "latitude": "51.515142",
    "crimeType": "Shoplifting"
  },
  {
    "timestamp": 1580515200.0,
    "longitude": "-0.079786",
    "latitude": "51.517576",
    "crimeType": "Shoplifting"
  },
  {
    "timestamp": 1580515200.0,
    "longitude": "-0.091720",
    "latitude": "51.513454",
    "crimeType": "Shoplifting"
  },
  {
    "timestamp": 1580515200.0,
    "longitude": "-0.100179",
    "latitude": "51.514158",
    "crimeType": "Theft from the person"
  },
  {
    "timestamp": 1580515200.0,
    "longitude": "-0.096900",
    "latitude": "51.510868",
    "crimeType": "Theft from the person"
  },
  {
    "timestamp": 1580515200.0,
    "longitude": "-0.101452",
    "latitude": "51.512650",
    "crimeType": "Theft from the person"
  },
  {
    "timestamp": 1580515200.0,
    "longitude": "-0.085833",
    "latitude": "51.513952",
    "crimeType": "Theft from the person"
  },
  {
    "timestamp": 1580515200.0,
    "longitude": "-0.096900",
    "latitude": "51.510868",
    "crimeType": "Theft from the person"
  },
  {
    "timestamp": 1580515200.0,
    "longitude": "-0.091108",
    "latitude": "51.511529",
    "crimeType": "Theft from the person"
  },
  {
    "timestamp": 1580515200.0,
    "longitude": "-0.090203",
    "latitude": "51.511118",
    "crimeType": "Theft from the person"
  },
  {
    "timestamp": 1580515200.0,
    "longitude": "-0.081620",
    "latitude": "51.516814",
    "crimeType": "Theft from the person"
  },
  {
    "timestamp": 1580515200.0,
    "longitude": "-0.084967",
    "latitude": "51.512598",
    "crimeType": "Theft from the person"
  },
  {
    "timestamp": 1580515200.0,
    "longitude": "-0.085149",
    "latitude": "51.517196",
    "crimeType": "Theft from the person"
  },
  {
    "timestamp": 1580515200.0,
    "longitude": "-0.081620",
    "latitude": "51.516814",
    "crimeType": "Theft from the person"
  },
  {
    "timestamp": 1580515200.0,
    "longitude": "-0.086166",
    "latitude": "51.510828",
    "crimeType": "Theft from the person"
  },
  {
    "timestamp": 1580515200.0,
    "longitude": "-0.096900",
    "latitude": "51.510868",
    "crimeType": "Theft from the person"
  },
  {
    "timestamp": 1580515200.0,
    "longitude": "-0.081281",
    "latitude": "51.512528",
    "crimeType": "Theft from the person"
  },
  {
    "timestamp": 1580515200.0,
    "longitude": "-0.078856",
    "latitude": "51.518433",
    "crimeType": "Theft from the person"
  },
  {
    "timestamp": 1580515200.0,
    "longitude": "-0.080782",
    "latitude": "51.514804",
    "crimeType": "Theft from the person"
  },
  {
    "timestamp": 1580515200.0,
    "longitude": "-0.084284",
    "latitude": "51.510671",
    "crimeType": "Theft from the person"
  },
  {
    "timestamp": 1580515200.0,
    "longitude": "-0.080376",
    "latitude": "51.517244",
    "crimeType": "Theft from the person"
  },
  {
    "timestamp": 1580515200.0,
    "longitude": "-0.100632",
    "latitude": "51.515739",
    "crimeType": "Theft from the person"
  },
  {
    "timestamp": 1580515200.0,
    "longitude": "-0.088843",
    "latitude": "51.509532",
    "crimeType": "Theft from the person"
  },
  {
    "timestamp": 1580515200.0,
    "longitude": "-0.083645",
    "latitude": "51.512504",
    "crimeType": "Theft from the person"
  },
  {
    "timestamp": 1580515200.0,
    "longitude": "-0.096814",
    "latitude": "51.512952",
    "crimeType": "Theft from the person"
  },
  {
    "timestamp": 1580515200.0,
    "longitude": "-0.090506",
    "latitude": "51.513524",
    "crimeType": "Theft from the person"
  },
  {
    "timestamp": 1580515200.0,
    "longitude": "-0.078924",
    "latitude": "51.508587",
    "crimeType": "Theft from the person"
  },
  {
    "timestamp": 1580515200.0,
    "longitude": "-0.101452",
    "latitude": "51.512650",
    "crimeType": "Theft from the person"
  },
  {
    "timestamp": 1580515200.0,
    "longitude": "-0.099716",
    "latitude": "51.511435",
    "crimeType": "Theft from the person"
  },
  {
    "timestamp": 1580515200.0,
    "longitude": "-0.086624",
    "latitude": "51.511923",
    "crimeType": "Theft from the person"
  },
  {
    "timestamp": 1580515200.0,
    "longitude": "-0.096814",
    "latitude": "51.512952",
    "crimeType": "Theft from the person"
  },
  {
    "timestamp": 1580515200.0,
    "longitude": "-0.089698",
    "latitude": "51.511812",
    "crimeType": "Theft from the person"
  },
  {
    "timestamp": 1580515200.0,
    "longitude": "-0.094628",
    "latitude": "51.514203",
    "crimeType": "Theft from the person"
  },
  {
    "timestamp": 1580515200.0,
    "longitude": "-0.086166",
    "latitude": "51.510828",
    "crimeType": "Theft from the person"
  },
  {
    "timestamp": 1580515200.0,
    "longitude": "-0.086166",
    "latitude": "51.510828",
    "crimeType": "Theft from the person"
  },
  {
    "timestamp": 1580515200.0,
    "longitude": "-0.089716",
    "latitude": "51.514501",
    "crimeType": "Theft from the person"
  },
  {
    "timestamp": 1580515200.0,
    "longitude": "-0.084967",
    "latitude": "51.512598",
    "crimeType": "Theft from the person"
  },
  {
    "timestamp": 1580515200.0,
    "longitude": "-0.089090",
    "latitude": "51.513258",
    "crimeType": "Theft from the person"
  },
  {
    "timestamp": 1580515200.0,
    "longitude": "-0.084284",
    "latitude": "51.510671",
    "crimeType": "Theft from the person"
  },
  {
    "timestamp": 1580515200.0,
    "longitude": "-0.098777",
    "latitude": "51.512526",
    "crimeType": "Theft from the person"
  },
  {
    "timestamp": 1580515200.0,
    "longitude": "-0.083386",
    "latitude": "51.509757",
    "crimeType": "Theft from the person"
  },
  {
    "timestamp": 1580515200.0,
    "longitude": "-0.082458",
    "latitude": "51.517431",
    "crimeType": "Theft from the person"
  },
  {
    "timestamp": 1580515200.0,
    "longitude": "-0.086624",
    "latitude": "51.511923",
    "crimeType": "Theft from the person"
  },
  {
    "timestamp": 1580515200.0,
    "longitude": "-0.094628",
    "latitude": "51.514203",
    "crimeType": "Theft from the person"
  },
  {
    "timestamp": 1580515200.0,
    "longitude": "-0.086166",
    "latitude": "51.510828",
    "crimeType": "Theft from the person"
  },
  {
    "timestamp": 1580515200.0,
    "longitude": "-0.089364",
    "latitude": "51.515331",
    "crimeType": "Theft from the person"
  },
  {
    "timestamp": 1580515200.0,
    "longitude": "-0.084284",
    "latitude": "51.510671",
    "crimeType": "Theft from the person"
  },
  {
    "timestamp": 1580515200.0,
    "longitude": "-0.089698",
    "latitude": "51.511812",
    "crimeType": "Theft from the person"
  },
  {
    "timestamp": 1580515200.0,
    "longitude": "-0.092077",
    "latitude": "51.512147",
    "crimeType": "Theft from the person"
  },
  {
    "timestamp": 1580515200.0,
    "longitude": "-0.096900",
    "latitude": "51.510868",
    "crimeType": "Theft from the person"
  },
  {
    "timestamp": 1580515200.0,
    "longitude": "-0.082458",
    "latitude": "51.517431",
    "crimeType": "Theft from the person"
  },
  {
    "timestamp": 1580515200.0,
    "longitude": "-0.079786",
    "latitude": "51.517576",
    "crimeType": "Theft from the person"
  },
  {
    "timestamp": 1580515200.0,
    "longitude": "-0.086278",
    "latitude": "51.509876",
    "crimeType": "Theft from the person"
  },
  {
    "timestamp": 1580515200.0,
    "longitude": "-0.081540",
    "latitude": "51.510806",
    "crimeType": "Theft from the person"
  },
  {
    "timestamp": 1580515200.0,
    "longitude": "-0.100179",
    "latitude": "51.514158",
    "crimeType": "Theft from the person"
  },
  {
    "timestamp": 1580515200.0,
    "longitude": "-0.082458",
    "latitude": "51.517431",
    "crimeType": "Theft from the person"
  },
  {
    "timestamp": 1580515200.0,
    "longitude": "-0.091151",
    "latitude": "51.514992",
    "crimeType": "Theft from the person"
  },
  {
    "timestamp": 1580515200.0,
    "longitude": "-0.081620",
    "latitude": "51.516814",
    "crimeType": "Theft from the person"
  },
  {
    "timestamp": 1580515200.0,
    "longitude": "-0.089090",
    "latitude": "51.513258",
    "crimeType": "Theft from the person"
  },
  {
    "timestamp": 1580515200.0,
    "longitude": "-0.089451",
    "latitude": "51.517032",
    "crimeType": "Theft from the person"
  },
  {
    "timestamp": 1580515200.0,
    "longitude": "-0.081620",
    "latitude": "51.516814",
    "crimeType": "Theft from the person"
  },
  {
    "timestamp": 1580515200.0,
    "longitude": "-0.085014",
    "latitude": "51.509775",
    "crimeType": "Vehicle crime"
  },
  {
    "timestamp": 1580515200.0,
    "longitude": "-0.092865",
    "latitude": "51.510182",
    "crimeType": "Vehicle crime"
  },
  {
    "timestamp": 1580515200.0,
    "longitude": "-0.087760",
    "latitude": "51.517149",
    "crimeType": "Vehicle crime"
  },
  {
    "timestamp": 1580515200.0,
    "longitude": "-0.078665",
    "latitude": "51.509950",
    "crimeType": "Vehicle crime"
  },
  {
    "timestamp": 1580515200.0,
    "longitude": "-0.078307",
    "latitude": "51.513676",
    "crimeType": "Vehicle crime"
  },
  {
    "timestamp": 1580515200.0,
    "longitude": "-0.093791",
    "latitude": "51.509414",
    "crimeType": "Vehicle crime"
  },
  {
    "timestamp": 1580515200.0,
    "longitude": "-0.079674",
    "latitude": "51.514409",
    "crimeType": "Vehicle crime"
  },
  {
    "timestamp": 1580515200.0,
    "longitude": "-0.092865",
    "latitude": "51.510182",
    "crimeType": "Vehicle crime"
  },
  {
    "timestamp": 1580515200.0,
    "longitude": "-0.078665",
    "latitude": "51.509950",
    "crimeType": "Vehicle crime"
  },
  {
    "timestamp": 1580515200.0,
    "longitude": "-0.077935",
    "latitude": "51.514281",
    "crimeType": "Vehicle crime"
  },
  {
    "timestamp": 1580515200.0,
    "longitude": "-0.082058",
    "latitude": "51.509466",
    "crimeType": "Vehicle crime"
  },
  {
    "timestamp": 1580515200.0,
    "longitude": "-0.096561",
    "latitude": "51.514513",
    "crimeType": "Violence and sexual offences"
  },
  {
    "timestamp": 1580515200.0,
    "longitude": "-0.082458",
    "latitude": "51.517431",
    "crimeType": "Violence and sexual offences"
  },
  {
    "timestamp": 1580515200.0,
    "longitude": "-0.079448",
    "latitude": "51.511554",
    "crimeType": "Violence and sexual offences"
  },
  {
    "timestamp": 1580515200.0,
    "longitude": "-0.081516",
    "latitude": "51.510014",
    "crimeType": "Violence and sexual offences"
  },
  {
    "timestamp": 1580515200.0,
    "longitude": "-0.083086",
    "latitude": "51.511407",
    "crimeType": "Violence and sexual offences"
  },
  {
    "timestamp": 1580515200.0,
    "longitude": "-0.083993",
    "latitude": "51.511440",
    "crimeType": "Violence and sexual offences"
  },
  {
    "timestamp": 1580515200.0,
    "longitude": "-0.079195",
    "latitude": "51.513798",
    "crimeType": "Violence and sexual offences"
  },
  {
    "timestamp": 1580515200.0,
    "longitude": "-0.076853",
    "latitude": "51.511916",
    "crimeType": "Violence and sexual offences"
  },
  {
    "timestamp": 1580515200.0,
    "longitude": "-0.097645",
    "latitude": "51.515142",
    "crimeType": "Violence and sexual offences"
  },
  {
    "timestamp": 1580515200.0,
    "longitude": "-0.081620",
    "latitude": "51.516814",
    "crimeType": "Violence and sexual offences"
  },
  {
    "timestamp": 1580515200.0,
    "longitude": "-0.080782",
    "latitude": "51.514804",
    "crimeType": "Violence and sexual offences"
  },
  {
    "timestamp": 1580515200.0,
    "longitude": "-0.081620",
    "latitude": "51.516814",
    "crimeType": "Violence and sexual offences"
  },
  {
    "timestamp": 1580515200.0,
    "longitude": "-0.083086",
    "latitude": "51.511407",
    "crimeType": "Violence and sexual offences"
  },
  {
    "timestamp": 1580515200.0,
    "longitude": "-0.087118",
    "latitude": "51.513199",
    "crimeType": "Violence and sexual offences"
  },
  {
    "timestamp": 1580515200.0,
    "longitude": "-0.082628",
    "latitude": "51.518189",
    "crimeType": "Violence and sexual offences"
  },
  {
    "timestamp": 1580515200.0,
    "longitude": "-0.087780",
    "latitude": "51.508066",
    "crimeType": "Violence and sexual offences"
  },
  {
    "timestamp": 1580515200.0,
    "longitude": "-0.093398",
    "latitude": "51.512951",
    "crimeType": "Violence and sexual offences"
  },
  {
    "timestamp": 1580515200.0,
    "longitude": "-0.097699",
    "latitude": "51.511420",
    "crimeType": "Violence and sexual offences"
  },
  {
    "timestamp": 1580515200.0,
    "longitude": "-0.081620",
    "latitude": "51.516814",
    "crimeType": "Violence and sexual offences"
  },
  {
    "timestamp": 1580515200.0,
    "longitude": "-0.094933",
    "latitude": "51.513129",
    "crimeType": "Violence and sexual offences"
  },
  {
    "timestamp": 1580515200.0,
    "longitude": "-0.080376",
    "latitude": "51.517244",
    "crimeType": "Violence and sexual offences"
  },
  {
    "timestamp": 1580515200.0,
    "longitude": "-0.081620",
    "latitude": "51.516814",
    "crimeType": "Violence and sexual offences"
  },
  {
    "timestamp": 1580515200.0,
    "longitude": "-0.081516",
    "latitude": "51.510014",
    "crimeType": "Violence and sexual offences"
  },
  {
    "timestamp": 1580515200.0,
    "longitude": "-0.100202",
    "latitude": "51.513268",
    "crimeType": "Violence and sexual offences"
  },
  {
    "timestamp": 1580515200.0,
    "longitude": "-0.090506",
    "latitude": "51.513524",
    "crimeType": "Violence and sexual offences"
  },
  {
    "timestamp": 1580515200.0,
    "longitude": "-0.088393",
    "latitude": "51.511332",
    "crimeType": "Violence and sexual offences"
  },
  {
    "timestamp": 1580515200.0,
    "longitude": "-0.100974",
    "latitude": "51.514450",
    "crimeType": "Violence and sexual offences"
  },
  {
    "timestamp": 1580515200.0,
    "longitude": "-0.087780",
    "latitude": "51.508066",
    "crimeType": "Violence and sexual offences"
  },
  {
    "timestamp": 1580515200.0,
    "longitude": "-0.092625",
    "latitude": "51.513865",
    "crimeType": "Violence and sexual offences"
  },
  {
    "timestamp": 1580515200.0,
    "longitude": "-0.081091",
    "latitude": "51.516014",
    "crimeType": "Violence and sexual offences"
  },
  {
    "timestamp": 1580515200.0,
    "longitude": "-0.084284",
    "latitude": "51.510671",
    "crimeType": "Violence and sexual offences"
  },
  {
    "timestamp": 1580515200.0,
    "longitude": "-0.084967",
    "latitude": "51.512598",
    "crimeType": "Violence and sexual offences"
  },
  {
    "timestamp": 1580515200.0,
    "longitude": "-0.092625",
    "latitude": "51.513865",
    "crimeType": "Violence and sexual offences"
  },
  {
    "timestamp": 1580515200.0,
    "longitude": "-0.079398",
    "latitude": "51.516508",
    "crimeType": "Violence and sexual offences"
  },
  {
    "timestamp": 1580515200.0,
    "longitude": "-0.082965",
    "latitude": "51.516351",
    "crimeType": "Violence and sexual offences"
  },
  {
    "timestamp": 1580515200.0,
    "longitude": "-0.082628",
    "latitude": "51.518189",
    "crimeType": "Violence and sexual offences"
  },
  {
    "timestamp": 1580515200.0,
    "longitude": "-0.082913",
    "latitude": "51.513463",
    "crimeType": "Violence and sexual offences"
  },
  {
    "timestamp": 1580515200.0,
    "longitude": "-0.076853",
    "latitude": "51.511916",
    "crimeType": "Violence and sexual offences"
  },
  {
    "timestamp": 1580515200.0,
    "longitude": "-0.082458",
    "latitude": "51.517431",
    "crimeType": "Violence and sexual offences"
  },
  {
    "timestamp": 1580515200.0,
    "longitude": "-0.081091",
    "latitude": "51.516014",
    "crimeType": "Violence and sexual offences"
  },
  {
    "timestamp": 1580515200.0,
    "longitude": "-0.081091",
    "latitude": "51.516014",
    "crimeType": "Violence and sexual offences"
  },
  {
    "timestamp": 1580515200.0,
    "longitude": "-0.079786",
    "latitude": "51.517576",
    "crimeType": "Violence and sexual offences"
  },
  {
    "timestamp": 1580515200.0,
    "longitude": "-0.086728",
    "latitude": "51.510477",
    "crimeType": "Violence and sexual offences"
  },
  {
    "timestamp": 1580515200.0,
    "longitude": "-0.082628",
    "latitude": "51.518189",
    "crimeType": "Violence and sexual offences"
  },
  {
    "timestamp": 1580515200.0,
    "longitude": "-0.082628",
    "latitude": "51.518189",
    "crimeType": "Violence and sexual offences"
  },
  {
    "timestamp": 1580515200.0,
    "longitude": "-0.096511",
    "latitude": "51.511922",
    "crimeType": "Violence and sexual offences"
  },
  {
    "timestamp": 1580515200.0,
    "longitude": "-0.077578",
    "latitude": "51.510795",
    "crimeType": "Violence and sexual offences"
  },
  {
    "timestamp": 1580515200.0,
    "longitude": "-0.081620",
    "latitude": "51.516814",
    "crimeType": "Violence and sexual offences"
  },
  {
    "timestamp": 1580515200.0,
    "longitude": "-0.090506",
    "latitude": "51.513524",
    "crimeType": "Violence and sexual offences"
  },
  {
    "timestamp": 1580515200.0,
    "longitude": "-0.090506",
    "latitude": "51.513524",
    "crimeType": "Violence and sexual offences"
  },
  {
    "timestamp": 1580515200.0,
    "longitude": "-0.081620",
    "latitude": "51.516814",
    "crimeType": "Violence and sexual offences"
  },
  {
    "timestamp": 1580515200.0,
    "longitude": "-0.094720",
    "latitude": "51.514420",
    "crimeType": "Violence and sexual offences"
  },
  {
    "timestamp": 1580515200.0,
    "longitude": "-0.092719",
    "latitude": "51.512652",
    "crimeType": "Violence and sexual offences"
  },
  {
    "timestamp": 1580515200.0,
    "longitude": "-0.081620",
    "latitude": "51.516814",
    "crimeType": "Violence and sexual offences"
  },
  {
    "timestamp": 1580515200.0,
    "longitude": "-0.087780",
    "latitude": "51.508066",
    "crimeType": "Violence and sexual offences"
  },
  {
    "timestamp": 1580515200.0,
    "longitude": "-0.081549",
    "latitude": "51.511625",
    "crimeType": "Other crime"
  },
  {
    "timestamp": 1580515200.0,
    "longitude": "-0.087780",
    "latitude": "51.508066",
    "crimeType": "Other crime"
  },
  {
    "timestamp": 1580515200.0,
    "longitude": "-0.081620",
    "latitude": "51.516814",
    "crimeType": "Other crime"
  },
  {
    "timestamp": 1580515200.0,
    "longitude": "-0.089435",
    "latitude": "51.511223",
    "crimeType": "Other crime"
  },
  {
    "timestamp": 1580515200.0,
    "longitude": "-0.104494",
    "latitude": "51.509848",
    "crimeType": "Other crime"
  },
  {
    "timestamp": 1580515200.0,
    "longitude": "-0.081620",
    "latitude": "51.516814",
    "crimeType": "Other crime"
  },
  {
    "timestamp": 1580515200.0,
    "longitude": "-0.108231",
    "latitude": "51.513928",
    "crimeType": "Anti-social behaviour"
  },
  {
    "timestamp": 1580515200.0,
    "longitude": "-0.105900",
    "latitude": "51.516966",
    "crimeType": "Anti-social behaviour"
  },
  {
    "timestamp": 1580515200.0,
    "longitude": "-0.104973",
    "latitude": "51.512887",
    "crimeType": "Anti-social behaviour"
  },
  {
    "timestamp": 1580515200.0,
    "longitude": "-0.105134",
    "latitude": "51.513869",
    "crimeType": "Anti-social behaviour"
  },
  {
    "timestamp": 1580515200.0,
    "longitude": "-0.108164",
    "latitude": "51.516571",
    "crimeType": "Anti-social behaviour"
  },
  {
    "timestamp": 1580515200.0,
    "longitude": "-0.105157",
    "latitude": "51.513330",
    "crimeType": "Anti-social behaviour"
  },
  {
    "timestamp": 1580515200.0,
    "longitude": "-0.105900",
    "latitude": "51.516966",
    "crimeType": "Anti-social behaviour"
  },
  {
    "timestamp": 1580515200.0,
    "longitude": "-0.109709",
    "latitude": "51.517909",
    "crimeType": "Anti-social behaviour"
  },
  {
    "timestamp": 1580515200.0,
    "longitude": "-0.107793",
    "latitude": "51.515450",
    "crimeType": "Bicycle theft"
  },
  {
    "timestamp": 1580515200.0,
    "longitude": "-0.108283",
    "latitude": "51.517526",
    "crimeType": "Bicycle theft"
  },
  {
    "timestamp": 1580515200.0,
    "longitude": "-0.102930",
    "latitude": "51.518375",
    "crimeType": "Bicycle theft"
  },
  {
    "timestamp": 1580515200.0,
    "longitude": "-0.101345",
    "latitude": "51.518709",
    "crimeType": "Bicycle theft"
  },
  {
    "timestamp": 1580515200.0,
    "longitude": "-0.104500",
    "latitude": "51.511449",
    "crimeType": "Bicycle theft"
  },
  {
    "timestamp": 1580515200.0,
    "longitude": "-0.098148",
    "latitude": "51.517938",
    "crimeType": "Bicycle theft"
  },
  {
    "timestamp": 1580515200.0,
    "longitude": "-0.102380",
    "latitude": "51.517728",
    "crimeType": "Bicycle theft"
  },
  {
    "timestamp": 1580515200.0,
    "longitude": "-0.105157",
    "latitude": "51.513330",
    "crimeType": "Bicycle theft"
  },
  {
    "timestamp": 1580515200.0,
    "longitude": "-0.106922",
    "latitude": "51.514204",
    "crimeType": "Bicycle theft"
  },
  {
    "timestamp": 1580515200.0,
    "longitude": "-0.106922",
    "latitude": "51.514204",
    "crimeType": "Bicycle theft"
  },
  {
    "timestamp": 1580515200.0,
    "longitude": "-0.106922",
    "latitude": "51.514204",
    "crimeType": "Bicycle theft"
  },
  {
    "timestamp": 1580515200.0,
    "longitude": "-0.102812",
    "latitude": "51.517042",
    "crimeType": "Bicycle theft"
  },
  {
    "timestamp": 1580515200.0,
    "longitude": "-0.102380",
    "latitude": "51.517728",
    "crimeType": "Burglary"
  },
  {
    "timestamp": 1580515200.0,
    "longitude": "-0.111181",
    "latitude": "51.516476",
    "crimeType": "Burglary"
  },
  {
    "timestamp": 1580515200.0,
    "longitude": "-0.104973",
    "latitude": "51.512887",
    "crimeType": "Burglary"
  },
  {
    "timestamp": 1580515200.0,
    "longitude": "-0.106357",
    "latitude": "51.512549",
    "crimeType": "Criminal damage and arson"
  },
  {
    "timestamp": 1580515200.0,
    "longitude": "-0.105134",
    "latitude": "51.513869",
    "crimeType": "Criminal damage and arson"
  },
  {
    "timestamp": 1580515200.0,
    "longitude": "-0.111181",
    "latitude": "51.516476",
    "crimeType": "Criminal damage and arson"
  },
  {
    "timestamp": 1580515200.0,
    "longitude": "-0.105900",
    "latitude": "51.516966",
    "crimeType": "Drugs"
  },
  {
    "timestamp": 1580515200.0,
    "longitude": "-0.098500",
    "latitude": "51.519526",
    "crimeType": "Other theft"
  },
  {
    "timestamp": 1580515200.0,
    "longitude": "-0.104252",
    "latitude": "51.516733",
    "crimeType": "Other theft"
  },
  {
    "timestamp": 1580515200.0,
    "longitude": "-0.100884",
    "latitude": "51.516966",
    "crimeType": "Other theft"
  },
  {
    "timestamp": 1580515200.0,
    "longitude": "-0.104300",
    "latitude": "51.511761",
    "crimeType": "Other theft"
  },
  {
    "timestamp": 1580515200.0,
    "longitude": "-0.098886",
    "latitude": "51.519254",
    "crimeType": "Other theft"
  },
  {
    "timestamp": 1580515200.0,
    "longitude": "-0.102741",
    "latitude": "51.513885",
    "crimeType": "Other theft"
  },
  {
    "timestamp": 1580515200.0,
    "longitude": "-0.108283",
    "latitude": "51.517526",
    "crimeType": "Other theft"
  },
  {
    "timestamp": 1580515200.0,
    "longitude": "-0.107793",
    "latitude": "51.515450",
    "crimeType": "Other theft"
  },
  {
    "timestamp": 1580515200.0,
    "longitude": "-0.112939",
    "latitude": "51.518231",
    "crimeType": "Other theft"
  },
  {
    "timestamp": 1580515200.0,
    "longitude": "-0.104281",
    "latitude": "51.516032",
    "crimeType": "Other theft"
  },
  {
    "timestamp": 1580515200.0,
    "longitude": "-0.105134",
    "latitude": "51.513869",
    "crimeType": "Other theft"
  },
  {
    "timestamp": 1580515200.0,
    "longitude": "-0.108965",
    "latitude": "51.516386",
    "crimeType": "Other theft"
  },
  {
    "timestamp": 1580515200.0,
    "longitude": "-0.106922",
    "latitude": "51.514204",
    "crimeType": "Other theft"
  },
  {
    "timestamp": 1580515200.0,
    "longitude": "-0.105134",
    "latitude": "51.513869",
    "crimeType": "Other theft"
  },
  {
    "timestamp": 1580515200.0,
    "longitude": "-0.105134",
    "latitude": "51.513869",
    "crimeType": "Other theft"
  },
  {
    "timestamp": 1580515200.0,
    "longitude": "-0.112519",
    "latitude": "51.517568",
    "crimeType": "Other theft"
  },
  {
    "timestamp": 1580515200.0,
    "longitude": "-0.104252",
    "latitude": "51.516733",
    "crimeType": "Other theft"
  },
  {
    "timestamp": 1580515200.0,
    "longitude": "-0.109647",
    "latitude": "51.514887",
    "crimeType": "Other theft"
  },
  {
    "timestamp": 1580515200.0,
    "longitude": "-0.105134",
    "latitude": "51.513869",
    "crimeType": "Other theft"
  },
  {
    "timestamp": 1580515200.0,
    "longitude": "-0.105134",
    "latitude": "51.513869",
    "crimeType": "Other theft"
  },
  {
    "timestamp": 1580515200.0,
    "longitude": "-0.102741",
    "latitude": "51.513885",
    "crimeType": "Other theft"
  },
  {
    "timestamp": 1580515200.0,
    "longitude": "-0.104300",
    "latitude": "51.511761",
    "crimeType": "Other theft"
  },
  {
    "timestamp": 1580515200.0,
    "longitude": "-0.102741",
    "latitude": "51.513885",
    "crimeType": "Other theft"
  },
  {
    "timestamp": 1580515200.0,
    "longitude": "-0.110710",
    "latitude": "51.513914",
    "crimeType": "Other theft"
  },
  {
    "timestamp": 1580515200.0,
    "longitude": "-0.097962",
    "latitude": "51.519635",
    "crimeType": "Other theft"
  },
  {
    "timestamp": 1580515200.0,
    "longitude": "-0.100884",
    "latitude": "51.516966",
    "crimeType": "Other theft"
  },
  {
    "timestamp": 1580515200.0,
    "longitude": "-0.112519",
    "latitude": "51.517568",
    "crimeType": "Other theft"
  },
  {
    "timestamp": 1580515200.0,
    "longitude": "-0.108018",
    "latitude": "51.511749",
    "crimeType": "Other theft"
  },
  {
    "timestamp": 1580515200.0,
    "longitude": "-0.108231",
    "latitude": "51.513928",
    "crimeType": "Other theft"
  },
  {
    "timestamp": 1580515200.0,
    "longitude": "-0.110710",
    "latitude": "51.513914",
    "crimeType": "Other theft"
  },
  {
    "timestamp": 1580515200.0,
    "longitude": "-0.102380",
    "latitude": "51.517728",
    "crimeType": "Public order"
  },
  {
    "timestamp": 1580515200.0,
    "longitude": "-0.102741",
    "latitude": "51.513885",
    "crimeType": "Public order"
  },
  {
    "timestamp": 1580515200.0,
    "longitude": "-0.104887",
    "latitude": "51.516347",
    "crimeType": "Public order"
  },
  {
    "timestamp": 1580515200.0,
    "longitude": "-0.100884",
    "latitude": "51.516966",
    "crimeType": "Public order"
  },
  {
    "timestamp": 1580515200.0,
    "longitude": "-0.109709",
    "latitude": "51.517909",
    "crimeType": "Robbery"
  },
  {
    "timestamp": 1580515200.0,
    "longitude": "-0.110710",
    "latitude": "51.513914",
    "crimeType": "Shoplifting"
  },
  {
    "timestamp": 1580515200.0,
    "longitude": "-0.108283",
    "latitude": "51.517526",
    "crimeType": "Shoplifting"
  },
  {
    "timestamp": 1580515200.0,
    "longitude": "-0.103280",
    "latitude": "51.514109",
    "crimeType": "Shoplifting"
  },
  {
    "timestamp": 1580515200.0,
    "longitude": "-0.104909",
    "latitude": "51.517912",
    "crimeType": "Theft from the person"
  },
  {
    "timestamp": 1580515200.0,
    "longitude": "-0.102812",
    "latitude": "51.517042",
    "crimeType": "Theft from the person"
  },
  {
    "timestamp": 1580515200.0,
    "longitude": "-0.104909",
    "latitude": "51.517912",
    "crimeType": "Theft from the person"
  },
  {
    "timestamp": 1580515200.0,
    "longitude": "-0.108965",
    "latitude": "51.516386",
    "crimeType": "Theft from the person"
  },
  {
    "timestamp": 1580515200.0,
    "longitude": "-0.098320",
    "latitude": "51.519344",
    "crimeType": "Theft from the person"
  },
  {
    "timestamp": 1580515200.0,
    "longitude": "-0.107148",
    "latitude": "51.511879",
    "crimeType": "Theft from the person"
  },
  {
    "timestamp": 1580515200.0,
    "longitude": "-0.105134",
    "latitude": "51.513869",
    "crimeType": "Theft from the person"
  },
  {
    "timestamp": 1580515200.0,
    "longitude": "-0.105900",
    "latitude": "51.516966",
    "crimeType": "Theft from the person"
  },
  {
    "timestamp": 1580515200.0,
    "longitude": "-0.111181",
    "latitude": "51.516476",
    "crimeType": "Theft from the person"
  },
  {
    "timestamp": 1580515200.0,
    "longitude": "-0.104909",
    "latitude": "51.517912",
    "crimeType": "Theft from the person"
  },
  {
    "timestamp": 1580515200.0,
    "longitude": "-0.104281",
    "latitude": "51.516032",
    "crimeType": "Theft from the person"
  },
  {
    "timestamp": 1580515200.0,
    "longitude": "-0.111181",
    "latitude": "51.516476",
    "crimeType": "Vehicle crime"
  },
  {
    "timestamp": 1580515200.0,
    "longitude": "-0.110471",
    "latitude": "51.517265",
    "crimeType": "Violence and sexual offences"
  },
  {
    "timestamp": 1580515200.0,
    "longitude": "-0.111132",
    "latitude": "51.512420",
    "crimeType": "Violence and sexual offences"
  },
  {
    "timestamp": 1580515200.0,
    "longitude": "-0.111132",
    "latitude": "51.512420",
    "crimeType": "Violence and sexual offences"
  },
  {
    "timestamp": 1580515200.0,
    "longitude": "-0.106680",
    "latitude": "51.515882",
    "crimeType": "Violence and sexual offences"
  },
  {
    "timestamp": 1580515200.0,
    "longitude": "-0.100884",
    "latitude": "51.516966",
    "crimeType": "Violence and sexual offences"
  },
  {
    "timestamp": 1580515200.0,
    "longitude": "-0.105561",
    "latitude": "51.510873",
    "crimeType": "Violence and sexual offences"
  },
  {
    "timestamp": 1580515200.0,
    "longitude": "-0.106680",
    "latitude": "51.515882",
    "crimeType": "Violence and sexual offences"
  },
  {
    "timestamp": 1580515200.0,
    "longitude": "-0.101345",
    "latitude": "51.518709",
    "crimeType": "Violence and sexual offences"
  },
  {
    "timestamp": 1580515200.0,
    "longitude": "-0.104887",
    "latitude": "51.516347",
    "crimeType": "Violence and sexual offences"
  },
  {
    "timestamp": 1580515200.0,
    "longitude": "-0.104973",
    "latitude": "51.512887",
    "crimeType": "Violence and sexual offences"
  },
  {
    "timestamp": 1580515200.0,
    "longitude": "-0.104281",
    "latitude": "51.516032",
    "crimeType": "Violence and sexual offences"
  },
  {
    "timestamp": 1580515200.0,
    "longitude": "-0.108231",
    "latitude": "51.513928",
    "crimeType": "Violence and sexual offences"
  },
  {
    "timestamp": 1580515200.0,
    "longitude": "-0.109709",
    "latitude": "51.517909",
    "crimeType": "Violence and sexual offences"
  },
  {
    "timestamp": 1580515200.0,
    "longitude": "-0.101320",
    "latitude": "51.519302",
    "crimeType": "Violence and sexual offences"
  },
  {
    "timestamp": 1580515200.0,
    "longitude": "-0.104973",
    "latitude": "51.512887",
    "crimeType": "Violence and sexual offences"
  },
  {
    "timestamp": 1580515200.0,
    "longitude": "-0.102794",
    "latitude": "51.515037",
    "crimeType": "Other crime"
  },
  {
    "timestamp": 1580515200.0,
    "longitude": "-0.108231",
    "latitude": "51.513928",
    "crimeType": "Other crime"
  },
  {
    "timestamp": 1580515200.0,
    "longitude": "-0.097210",
    "latitude": "51.523156",
    "crimeType": "Theft from the person"
  },
  {
    "timestamp": 1580515200.0,
    "longitude": "-0.101649",
    "latitude": "51.519703",
    "crimeType": "Violence and sexual offences"
  },
  {
    "timestamp": 1580515200.0,
    "longitude": "-0.088440",
    "latitude": "51.519507",
    "crimeType": "Bicycle theft"
  },
  {
    "timestamp": 1580515200.0,
    "longitude": "-0.091732",
    "latitude": "51.521080",
    "crimeType": "Theft from the person"
  },
  {
    "timestamp": 1580515200.0,
    "longitude": "-0.091732",
    "latitude": "51.521080",
    "crimeType": "Theft from the person"
  },
  {
    "timestamp": 1580515200.0,
    "longitude": "-0.094959",
    "latitude": "51.522868",
    "crimeType": "Anti-social behaviour"
  },
  {
    "timestamp": 1580515200.0,
    "longitude": "-0.096315",
    "latitude": "51.508313",
    "crimeType": "Theft from the person"
  },
  {
    "timestamp": 1580515200.0,
    "longitude": "-0.076437",
    "latitude": "51.519050",
    "crimeType": "Bicycle theft"
  },
  {
    "timestamp": 1580515200.0,
    "longitude": "-0.077601",
    "latitude": "51.518799",
    "crimeType": "Theft from the person"
  },
  {
    "timestamp": 1580515200.0,
    "longitude": "-0.079130",
    "latitude": "51.507808",
    "crimeType": "Anti-social behaviour"
  },
  {
    "timestamp": 1580515200.0,
    "longitude": "-0.079130",
    "latitude": "51.507808",
    "crimeType": "Other theft"
  },
  {
    "timestamp": 1580515200.0,
    "longitude": "-0.074901",
    "latitude": "51.506255",
    "crimeType": "Other theft"
  },
  {
    "timestamp": 1580515200.0,
    "longitude": "-0.079130",
    "latitude": "51.507808",
    "crimeType": "Other theft"
  },
  {
    "timestamp": 1580515200.0,
    "longitude": "-0.079130",
    "latitude": "51.507808",
    "crimeType": "Other theft"
  },
  {
    "timestamp": 1580515200.0,
    "longitude": "-0.074901",
    "latitude": "51.506255",
    "crimeType": "Public order"
  },
  {
    "timestamp": 1580515200.0,
    "longitude": "-0.074901",
    "latitude": "51.506255",
    "crimeType": "Theft from the person"
  },
  {
    "timestamp": 1580515200.0,
    "longitude": "-0.074901",
    "latitude": "51.506255",
    "crimeType": "Theft from the person"
  },
  {
    "timestamp": 1580515200.0,
    "longitude": "-0.074901",
    "latitude": "51.506255",
    "crimeType": "Violence and sexual offences"
  },
  {
    "timestamp": 1580515200.0,
    "longitude": "-0.111974",
    "latitude": "51.513683",
    "crimeType": "Bicycle theft"
  },
  {
    "timestamp": 1580515200.0,
    "longitude": "-0.111974",
    "latitude": "51.513683",
    "crimeType": "Burglary"
  },
  {
    "timestamp": 1580515200.0,
    "longitude": "-0.121813",
    "latitude": "51.507133",
    "crimeType": "Drugs"
  },
  {
    "timestamp": 1580515200.0,
    "longitude": "-0.121813",
    "latitude": "51.507133",
    "crimeType": "Theft from the person"
  },
  {
    "timestamp": 1580515200.0,
    "longitude": "-0.121813",
    "latitude": "51.507133",
    "crimeType": "Other crime"
  }
]